<?xml version="1.0" encoding="utf-8"?>
<VocabularyDatabase xmlns:xsi="http://www.w3.org/2001/XMLSchema-instance" xmlns:xsd="http://www.w3.org/2001/XMLSchema">
  <Database>
    <Vocabulary>
      <german>Guten Tag</german>
      <japanese>こんにちは</japanese>
      <romaji>konnichiha</romaji>
      <cat>Ausdruck</cat>
      <lection>1</lection>
    </Vocabulary>
    <Vocabulary>
      <german>Guten Abend</german>
      <japanese>こんばんは</japanese>
      <romaji>konbanha</romaji>
      <cat>Ausdruck</cat>
      <lection>1</lection>
    </Vocabulary>
    <Vocabulary>
      <german>Guten Morgen</german>
      <japanese>おはようございます</japanese>
      <romaji>ohayoo gozaimasu</romaji>
      <cat>Ausdruck</cat>
      <lection>1</lection>
    </Vocabulary>
    <Vocabulary>
      <german>aufstehen</german>
      <japanese>おきます</japanese>
      <romaji>okimasu</romaji>
      <cat>Verben</cat>
      <lection>9</lection>
    </Vocabulary>
    <Vocabulary>
      <german>schlafen</german>
      <japanese>ねます</japanese>
      <romaji>nemasu</romaji>
      <cat>Verben</cat>
      <lection>9</lection>
    </Vocabulary>
    <Vocabulary>
      <german>machen</german>
      <japanese>します</japanese>
      <romaji>shimasu</romaji>
      <cat>Verben</cat>
      <lection>9</lection>
    </Vocabulary>
    <Vocabulary>
      <german>gehen</german>
      <japanese>行きます</japanese>
      <romaji>ikimasu</romaji>
      <cat>Verben</cat>
      <lection>9</lection>
    </Vocabulary>
    <Vocabulary>
      <german>lernen</german>
      <japanese>べんきょうします</japanese>
      <romaji>benkyoo-shimasu</romaji>
      <cat>Verben</cat>
      <lection>9</lection>
    </Vocabulary>
    <Vocabulary>
      <german>sehen</german>
      <japanese>見ます</japanese>
      <romaji>mimasu</romaji>
      <cat>Verben</cat>
      <lection>9</lection>
    </Vocabulary>
    <Vocabulary>
      <german>hören</german>
      <japanese>聞きます</japanese>
      <romaji>kikimasu</romaji>
      <cat>Verben</cat>
      <lection>9</lection>
    </Vocabulary>
    <Vocabulary>
      <german>lesen</german>
      <japanese>読みます</japanese>
      <romaji>yomimasu</romaji>
      <cat>Verben</cat>
      <lection>9</lection>
    </Vocabulary>
    <Vocabulary>
      <german>schreiben</german>
      <japanese>書きます</japanese>
      <romaji>kakimasu</romaji>
      <cat>Verben</cat>
      <lection>9</lection>
    </Vocabulary>
    <Vocabulary>
      <german>hineinsteigen</german>
      <japanese>はいります</japanese>
      <romaji>hairimasu</romaji>
      <cat>Verben</cat>
      <lection>9</lection>
    </Vocabulary>
    <Vocabulary>
      <german>baden</german>
      <japanese>おふろ　に　はいります</japanese>
      <romaji>ofuro ni hairimasu</romaji>
      <cat>Verben</cat>
      <lection>9</lection>
    </Vocabulary>
    <Vocabulary>
      <german>heimkehren</german>
      <japanese>帰ります</japanese>
      <romaji>kaerimasu</romaji>
      <cat>Verben</cat>
      <lection>9</lection>
    </Vocabulary>
    <Vocabulary>
      <german>Sport</german>
      <japanese>うんどう</japanese>
      <romaji>undoo</romaji>
      <cat>Nomen</cat>
      <lection>9</lection>
    </Vocabulary>
    <Vocabulary>
      <german>Firma</german>
      <japanese>かいしゃ</japanese>
      <romaji>kaisha</romaji>
      <cat>Nomen</cat>
      <lection>9</lection>
    </Vocabulary>
    <Vocabulary>
      <german>Spaziergang</german>
      <japanese>さんぽ</japanese>
      <romaji>sanpo</romaji>
      <cat>Nomen</cat>
      <lection>9</lection>
    </Vocabulary>
    <Vocabulary>
      <german>Schule</german>
      <japanese>がっこう</japanese>
      <romaji>gakkoo</romaji>
      <cat>Nomen</cat>
      <lection>9</lection>
    </Vocabulary>
    <Vocabulary>
      <german>Arbeit</german>
      <japanese>しごと</japanese>
      <romaji>shigoto</romaji>
      <cat>Nomen</cat>
      <lection>1</lection>
    </Vocabulary>
    <Vocabulary>
      <german>Musik</german>
      <japanese>おんがく</japanese>
      <romaji>ongaku</romaji>
      <cat>Nomen</cat>
      <lection>9</lection>
    </Vocabulary>
    <Vocabulary>
      <german>Zeitung</german>
      <japanese>しんぶん</japanese>
      <romaji>shinbun</romaji>
      <cat>Nomen</cat>
      <lection>9</lection>
    </Vocabulary>
    <Vocabulary>
      <german>Tagebuch</german>
      <japanese>にっき</japanese>
      <romaji>nikki</romaji>
      <cat>Nomen</cat>
      <lection>9</lection>
    </Vocabulary>
    <Vocabulary>
      <german>Haushalt</german>
      <japanese>かじ</japanese>
      <romaji>kaji</romaji>
      <cat>Nomen</cat>
      <lection>9</lection>
    </Vocabulary>
    <Vocabulary>
      <german>Badewanne</german>
      <japanese>おふろ</japanese>
      <romaji>ofuro</romaji>
      <cat>Nomen</cat>
      <lection>9</lection>
    </Vocabulary>
    <Vocabulary>
      <german>Haus/Zuhause</german>
      <japanese>うち</japanese>
      <romaji>uchi</romaji>
      <cat>Nomen</cat>
      <lection>9</lection>
    </Vocabulary>
    <Vocabulary>
      <german>jeden Tag</german>
      <japanese>まいにち</japanese>
      <romaji>mainichi</romaji>
      <cat>Zeitwörter</cat>
      <lection>9</lection>
    </Vocabulary>
    <Vocabulary>
      <german>~Uhr</german>
      <japanese>じ</japanese>
      <romaji>ji</romaji>
      <cat>Zeitwörter</cat>
      <lection>9</lection>
    </Vocabulary>
    <Vocabulary>
      <german>30 Minuten nach</german>
      <japanese>はん</japanese>
      <romaji>han</romaji>
      <cat>Zeitwörter</cat>
      <lection>9</lection>
    </Vocabulary>
    <Vocabulary>
      <german>beschäftigt</german>
      <japanese>いそがしい</japanese>
      <romaji>isogashii</romaji>
      <cat>Adjektiv</cat>
      <lection>9</lection>
    </Vocabulary>
    <Vocabulary>
      <german>morgens</german>
      <japanese>あさ</japanese>
      <romaji>asa</romaji>
      <cat>Zeitwörter</cat>
      <lection>9</lection>
    </Vocabulary>
    <Vocabulary>
      <german>mittags</german>
      <japanese>ひる</japanese>
      <romaji>hiru</romaji>
      <cat>Zeitwörter</cat>
      <lection>9</lection>
    </Vocabulary>
    <Vocabulary>
      <german>abends</german>
      <japanese>よる</japanese>
      <romaji>yoru</romaji>
      <cat>Zeitwörter</cat>
      <lection>9</lection>
    </Vocabulary>
    <Vocabulary>
      <german>gegen</german>
      <japanese>ごろ</japanese>
      <romaji>goro</romaji>
      <cat>Zeitwörter</cat>
      <lection>9</lection>
    </Vocabulary>
    <Vocabulary>
      <german>duschen</german>
      <japanese>シャワー を　あびます</japanese>
      <romaji>shawaa o abimasu</romaji>
      <cat>Verben</cat>
      <lection>9</lection>
    </Vocabulary>
    <Vocabulary>
      <german>~Minute</german>
      <japanese>ぷん　/ ふん</japanese>
      <romaji>pun / fun</romaji>
      <cat>Zeitwörter</cat>
      <lection>9</lection>
    </Vocabulary>
    <Vocabulary>
      <german>a.m.</german>
      <japanese>ごぜん</japanese>
      <romaji>gozen</romaji>
      <cat>Zeitwörter</cat>
      <lection>9</lection>
    </Vocabulary>
    <Vocabulary>
      <german>p.m.</german>
      <japanese>ごご</japanese>
      <romaji>gogo</romaji>
      <cat>Zeitwörter</cat>
      <lection>9</lection>
    </Vocabulary>
    <Vocabulary>
      <german>Tagesablauf</german>
      <japanese>いちにち</japanese>
      <romaji>ichinichi</romaji>
      <cat>Nomen</cat>
      <lection>9</lection>
    </Vocabulary>
    <Vocabulary>
      <german>Mahlzeit</german>
      <japanese>しょくじ</japanese>
      <romaji>shokuji</romaji>
      <cat>Nomen</cat>
      <lection>10</lection>
    </Vocabulary>
    <Vocabulary>
      <german>Einkaufen</german>
      <japanese>かいもの</japanese>
      <romaji>kaimono</romaji>
      <cat>Nomen</cat>
      <lection>10</lection>
    </Vocabulary>
    <Vocabulary>
      <german>Krankenhaus</german>
      <japanese>びょういん</japanese>
      <romaji>byooin</romaji>
      <cat>Nomen</cat>
      <lection>10</lection>
    </Vocabulary>
    <Vocabulary>
      <german>Kunstmuseum</german>
      <japanese>びじゅつかん</japanese>
      <romaji>bijutsukan</romaji>
      <cat>Nomen</cat>
      <lection>10</lection>
    </Vocabulary>
    <Vocabulary>
      <german>Montag</german>
      <japanese>月よう日</japanese>
      <romaji>getsuyoobi</romaji>
      <cat>Zeitwörter</cat>
      <lection>10</lection>
    </Vocabulary>
    <Vocabulary>
      <german>Dienstag</german>
      <japanese>火よう日</japanese>
      <romaji>kayoobi</romaji>
      <cat>Zeitwörter</cat>
      <lection>10</lection>
    </Vocabulary>
    <Vocabulary>
      <german>Mittwoch</german>
      <japanese>水よう日</japanese>
      <romaji>suiyoobi</romaji>
      <cat>Zeitwörter</cat>
      <lection>10</lection>
    </Vocabulary>
    <Vocabulary>
      <german>Donnerstag</german>
      <japanese>木よう日</japanese>
      <romaji>mokuyoobi</romaji>
      <cat>Zeitwörter</cat>
      <lection>10</lection>
    </Vocabulary>
    <Vocabulary>
      <german>Freitag</german>
      <japanese>金よう日</japanese>
      <romaji>Kin'yoobi</romaji>
      <cat>Zeitwörter</cat>
      <lection>10</lection>
    </Vocabulary>
    <Vocabulary>
      <german>Samstag</german>
      <japanese>土よう日</japanese>
      <romaji>doyoobi</romaji>
      <cat>Zeitwörter</cat>
      <lection>10</lection>
    </Vocabulary>
    <Vocabulary>
      <german>Sonntag</german>
      <japanese>日よう日</japanese>
      <romaji>nichiyoobi</romaji>
      <cat>Zeitwörter</cat>
      <lection>10</lection>
    </Vocabulary>
    <Vocabulary>
      <german>Letzte Woche</german>
      <japanese>せんしゅう</japanese>
      <romaji>senshuu</romaji>
      <cat>Zeitwörter</cat>
      <lection>10</lection>
    </Vocabulary>
    <Vocabulary>
      <german>Diese Woche</german>
      <japanese>こんしゅう</japanese>
      <romaji>konshuu</romaji>
      <cat>Zeitwörter</cat>
      <lection>10</lection>
    </Vocabulary>
    <Vocabulary>
      <german>Nächste Woche</german>
      <japanese>らいしゅう</japanese>
      <romaji>raishuu</romaji>
      <cat>Zeitwörter</cat>
      <lection>10</lection>
    </Vocabulary>
    <Vocabulary>
      <german>gestern</german>
      <japanese>きのう</japanese>
      <romaji>kinoo</romaji>
      <cat>Zeitwörter</cat>
      <lection>10</lection>
    </Vocabulary>
    <Vocabulary>
      <german>heute</german>
      <japanese>きょう</japanese>
      <romaji>kyoo</romaji>
      <cat>Zeitwörter</cat>
      <lection>10</lection>
    </Vocabulary>
    <Vocabulary>
      <german>morgen</german>
      <japanese>あした</japanese>
      <romaji>ashita</romaji>
      <cat>Zeitwörter</cat>
      <lection>10</lection>
    </Vocabulary>
    <Vocabulary>
      <german>ausruhen</german>
      <japanese>やすみます</japanese>
      <romaji>yasumimasu</romaji>
      <cat>Verben</cat>
      <lection>9</lection>
    </Vocabulary>
    <Vocabulary>
      <german>Universität</german>
      <japanese>だいがく</japanese>
      <romaji>daigaku</romaji>
      <cat>Nomen</cat>
      <lection>1</lection>
    </Vocabulary>
    <Vocabulary>
      <german>Kaufhaus</german>
      <japanese>デパート</japanese>
      <romaji>depaato</romaji>
      <cat>Nomen</cat>
      <lection>11</lection>
    </Vocabulary>
    <Vocabulary>
      <german>draußen</german>
      <japanese>そと</japanese>
      <romaji>soto</romaji>
      <cat>Adjektiv</cat>
      <lection>11</lection>
    </Vocabulary>
    <Vocabulary>
      <german>Raum / Zimmer</german>
      <japanese>へや</japanese>
      <romaji>heya</romaji>
      <cat>Nomen</cat>
      <lection>11</lection>
    </Vocabulary>
    <Vocabulary>
      <german>Toilette</german>
      <japanese>トイレ</japanese>
      <romaji>toire</romaji>
      <cat>Nomen</cat>
      <lection>11</lection>
    </Vocabulary>
    <Vocabulary>
      <german>Park</german>
      <japanese>こうえん</japanese>
      <romaji>kooen</romaji>
      <cat>Nomen</cat>
      <lection>11</lection>
    </Vocabulary>
    <Vocabulary>
      <german>Tempel</german>
      <japanese>おてら</japanese>
      <romaji>otera</romaji>
      <cat>Nomen</cat>
      <lection>11</lection>
    </Vocabulary>
    <Vocabulary>
      <german>Bahnhof</german>
      <japanese>えき</japanese>
      <romaji>eki</romaji>
      <cat>Nomen</cat>
      <lection>11</lection>
    </Vocabulary>
    <Vocabulary>
      <german>Film</german>
      <japanese>えいが</japanese>
      <romaji>eega</romaji>
      <cat>Nomen</cat>
      <lection>11</lection>
    </Vocabulary>
    <Vocabulary>
      <german>Fremdsprache</german>
      <japanese>がいこく語</japanese>
      <romaji>daikokugo</romaji>
      <cat>Nomen</cat>
      <lection>11</lection>
    </Vocabulary>
    <Vocabulary>
      <german>Fotografie</german>
      <japanese>しゃしん</japanese>
      <romaji>shashin</romaji>
      <cat>Nomen</cat>
      <lection>11</lection>
    </Vocabulary>
    <Vocabulary>
      <german>nehmen</german>
      <japanese>とります</japanese>
      <romaji>torimasu</romaji>
      <cat>Verben</cat>
      <lection>11</lection>
    </Vocabulary>
    <Vocabulary>
      <german>langsam</german>
      <japanese>ゆっくり</japanese>
      <romaji>yukkuri</romaji>
      <cat>Adverb</cat>
      <lection>11</lection>
    </Vocabulary>
    <Vocabulary>
      <german>Plan</german>
      <japanese>よてい</japanese>
      <romaji>yotee</romaji>
      <cat>Nomen</cat>
      <lection>11</lection>
    </Vocabulary>
    <Vocabulary>
      <german>Überstunde</german>
      <japanese>ざんきょう</japanese>
      <romaji>zankyoo</romaji>
      <cat>Nomen</cat>
      <lection>11</lection>
    </Vocabulary>
    <Vocabulary>
      <german>Terminkalender</german>
      <japanese>てちょう</japanese>
      <romaji>techoo</romaji>
      <cat>Nomen</cat>
      <lection>11</lection>
    </Vocabulary>
    <Vocabulary>
      <german>gut passen</german>
      <japanese>いいです</japanese>
      <romaji>iidesu</romaji>
      <cat>Verben</cat>
      <lection>10</lection>
    </Vocabulary>
    <Vocabulary>
      <german>nicht passen</german>
      <japanese>だめです</japanese>
      <romaji>dame desu</romaji>
      <cat>Verben</cat>
      <lection>10</lection>
    </Vocabulary>
    <Vocabulary>
      <german>in Ordnung sein</german>
      <japanese>だいじょうぶです</japanese>
      <romaji>daijoobu desu</romaji>
      <cat>Verben</cat>
      <lection>10</lection>
    </Vocabulary>
    <Vocabulary>
      <german>immer passen</german>
      <japanese>いつでも　いいです</japanese>
      <romaji>itsudemo iidesu</romaji>
      <cat>Verben</cat>
      <lection>10</lection>
    </Vocabulary>
    <Vocabulary>
      <german>Regen</german>
      <japanese>あめ</japanese>
      <romaji>ame</romaji>
      <cat>Nomen</cat>
      <lection>Andere</lection>
    </Vocabulary>
    <Vocabulary>
      <german>Wind</german>
      <japanese>かぜ</japanese>
      <romaji>kaze</romaji>
      <cat>Nomen</cat>
      <lection>Andere</lection>
    </Vocabulary>
    <Vocabulary>
      <german>Wetter</german>
      <japanese>てんき</japanese>
      <romaji>tenki</romaji>
      <cat>Nomen</cat>
      <lection>Andere</lection>
    </Vocabulary>
    <Vocabulary>
      <german>Liebesgeschichte</german>
      <japanese>れんあい</japanese>
      <romaji>ren'ai</romaji>
      <cat>Nomen</cat>
      <lection>11</lection>
    </Vocabulary>
    <Vocabulary>
      <german>Klassik</german>
      <japanese>クラシック</japanese>
      <romaji>kurasikku</romaji>
      <cat>Nomen</cat>
      <lection>11</lection>
    </Vocabulary>
    <Vocabulary>
      <german>Action</german>
      <japanese>アクション</japanese>
      <romaji>akushion</romaji>
      <cat>Nomen</cat>
      <lection>11</lection>
    </Vocabulary>
    <Vocabulary>
      <german>Baseball</german>
      <japanese>やきゅう</japanese>
      <romaji>yakyuu</romaji>
      <cat>Nomen</cat>
      <lection>11</lection>
    </Vocabulary>
    <Vocabulary>
      <german>Judo</german>
      <japanese>じゅうどう</japanese>
      <romaji>juudoo</romaji>
      <cat>Nomen</cat>
      <lection>11</lection>
    </Vocabulary>
    <Vocabulary>
      <german>Hobby</german>
      <japanese>しゅみ</japanese>
      <romaji>shumi</romaji>
      <cat>Nomen</cat>
      <lection>11</lection>
    </Vocabulary>
    <Vocabulary>
      <german>sprechen</german>
      <japanese>話します</japanese>
      <romaji>hanachimasu</romaji>
      <cat>Verben</cat>
      <lection>11</lection>
    </Vocabulary>
    <Vocabulary>
      <german>sagen</german>
      <japanese>言います</japanese>
      <romaji>iimasu</romaji>
      <cat>Verben</cat>
      <lection>11</lection>
    </Vocabulary>
    <Vocabulary>
      <german>~Monat</german>
      <japanese>月</japanese>
      <romaji>gatsu</romaji>
      <cat>Zeitwörter</cat>
      <lection>11</lection>
    </Vocabulary>
    <Vocabulary>
      <german>~Tag</german>
      <japanese>日</japanese>
      <romaji>nichi</romaji>
      <cat>Zeitwörter</cat>
      <lection>11</lection>
    </Vocabulary>
    <Vocabulary>
      <german>Erster im Monat</german>
      <japanese>ついたち</japanese>
      <romaji>tsuitachi</romaji>
      <cat>Zeitwörter</cat>
      <lection>11</lection>
    </Vocabulary>
    <Vocabulary>
      <german>Zweiter im Monat</german>
      <japanese>ふつか</japanese>
      <romaji>futsuka</romaji>
      <cat>Zeitwörter</cat>
      <lection>11</lection>
    </Vocabulary>
    <Vocabulary>
      <german>Dritter im Monat</german>
      <japanese>みっか</japanese>
      <romaji>mikka</romaji>
      <cat>Zeitwörter</cat>
      <lection>11</lection>
    </Vocabulary>
    <Vocabulary>
      <german>Vierter im Monat</german>
      <japanese>よっか</japanese>
      <romaji>yokka</romaji>
      <cat>Zeitwörter</cat>
      <lection>11</lection>
    </Vocabulary>
    <Vocabulary>
      <german>Fünfter im Monat</german>
      <japanese>いつか</japanese>
      <romaji>itsuka</romaji>
      <cat>Zeitwörter</cat>
      <lection>11</lection>
    </Vocabulary>
    <Vocabulary>
      <german>Sechster im Monat</german>
      <japanese>むいか</japanese>
      <romaji>muika</romaji>
      <cat>Zeitwörter</cat>
      <lection>11</lection>
    </Vocabulary>
    <Vocabulary>
      <german>Siebter im Monat</german>
      <japanese>なのか</japanese>
      <romaji>nanoka</romaji>
      <cat>Zeitwörter</cat>
      <lection>11</lection>
    </Vocabulary>
    <Vocabulary>
      <german>Achter im Monat</german>
      <japanese>ようか</japanese>
      <romaji>yooka</romaji>
      <cat>Zeitwörter</cat>
      <lection>11</lection>
    </Vocabulary>
    <Vocabulary>
      <german>Neunter im Monat</german>
      <japanese>ここのか</japanese>
      <romaji>kokonoka</romaji>
      <cat>Zeitwörter</cat>
      <lection>11</lection>
    </Vocabulary>
    <Vocabulary>
      <german>Zehnter im Monat</german>
      <japanese>とおか</japanese>
      <romaji>tooka</romaji>
      <cat>Zeitwörter</cat>
      <lection>11</lection>
    </Vocabulary>
    <Vocabulary>
      <german>wann</german>
      <japanese>いつ</japanese>
      <romaji>itsu</romaji>
      <cat>Fragewörter</cat>
      <lection>10</lection>
    </Vocabulary>
    <Vocabulary>
      <german>a</german>
      <japanese>ア</japanese>
      <romaji>a</romaji>
      <cat>Schriftzeichen</cat>
      <lection>Katakana</lection>
    </Vocabulary>
    <Vocabulary>
      <german>i</german>
      <japanese>イ</japanese>
      <romaji>i</romaji>
      <cat>Schriftzeichen</cat>
      <lection>Katakana</lection>
    </Vocabulary>
    <Vocabulary>
      <german>u</german>
      <japanese>ウ</japanese>
      <romaji>u</romaji>
      <cat>Schriftzeichen</cat>
      <lection>Katakana</lection>
    </Vocabulary>
    <Vocabulary>
      <german>e</german>
      <japanese>エ</japanese>
      <romaji>e</romaji>
      <cat>Schriftzeichen</cat>
      <lection>Katakana</lection>
    </Vocabulary>
    <Vocabulary>
      <german>o</german>
      <japanese>オ</japanese>
      <romaji>o</romaji>
      <cat>Schriftzeichen</cat>
      <lection>Katakana</lection>
    </Vocabulary>
    <Vocabulary>
      <german>ka</german>
      <japanese>カ</japanese>
      <romaji>ka</romaji>
      <cat>Schriftzeichen</cat>
      <lection>Katakana</lection>
    </Vocabulary>
    <Vocabulary>
      <german>ki</german>
      <japanese>キ</japanese>
      <romaji>ki</romaji>
      <cat>Schriftzeichen</cat>
      <lection>Katakana</lection>
    </Vocabulary>
    <Vocabulary>
      <german>ku</german>
      <japanese>ク</japanese>
      <romaji>ku</romaji>
      <cat>Schriftzeichen</cat>
      <lection>Katakana</lection>
    </Vocabulary>
    <Vocabulary>
      <german>ke</german>
      <japanese>ケ</japanese>
      <romaji>ke</romaji>
      <cat>Schriftzeichen</cat>
      <lection>Katakana</lection>
    </Vocabulary>
    <Vocabulary>
      <german>ko</german>
      <japanese>コ</japanese>
      <romaji>ko</romaji>
      <cat>Schriftzeichen</cat>
      <lection>Katakana</lection>
    </Vocabulary>
    <Vocabulary>
      <german>sa</german>
      <japanese>サ</japanese>
      <romaji>sa</romaji>
      <cat>Schriftzeichen</cat>
      <lection>Katakana</lection>
    </Vocabulary>
    <Vocabulary>
      <german>shi</german>
      <japanese>シ</japanese>
      <romaji>shi</romaji>
      <cat>Schriftzeichen</cat>
      <lection>Katakana</lection>
    </Vocabulary>
    <Vocabulary>
      <german>su</german>
      <japanese>ス</japanese>
      <romaji>su</romaji>
      <cat>Schriftzeichen</cat>
      <lection>Katakana</lection>
    </Vocabulary>
    <Vocabulary>
      <german>se</german>
      <japanese>セ</japanese>
      <romaji>se</romaji>
      <cat>Schriftzeichen</cat>
      <lection>Katakana</lection>
    </Vocabulary>
    <Vocabulary>
      <german>so</german>
      <japanese>ソ</japanese>
      <romaji>so</romaji>
      <cat>Schriftzeichen</cat>
      <lection>Katakana</lection>
    </Vocabulary>
    <Vocabulary>
      <german>ta</german>
      <japanese>タ</japanese>
      <romaji>ta</romaji>
      <cat>Schriftzeichen</cat>
      <lection>Katakana</lection>
    </Vocabulary>
    <Vocabulary>
      <german>chi</german>
      <japanese>チ</japanese>
      <romaji>chi</romaji>
      <cat>Schriftzeichen</cat>
      <lection>Katakana</lection>
    </Vocabulary>
    <Vocabulary>
      <german>tsu</german>
      <japanese>ツ</japanese>
      <romaji>tsu</romaji>
      <cat>Schriftzeichen</cat>
      <lection>Katakana</lection>
    </Vocabulary>
    <Vocabulary>
      <german>te</german>
      <japanese>テ</japanese>
      <romaji>te</romaji>
      <cat>Schriftzeichen</cat>
      <lection>Katakana</lection>
    </Vocabulary>
    <Vocabulary>
      <german>to</german>
      <japanese>ト</japanese>
      <romaji>to</romaji>
      <cat>Schriftzeichen</cat>
      <lection>Katakana</lection>
    </Vocabulary>
    <Vocabulary>
      <german>na</german>
      <japanese>ナ</japanese>
      <romaji>na</romaji>
      <cat>Schriftzeichen</cat>
      <lection>Katakana</lection>
    </Vocabulary>
    <Vocabulary>
      <german>ni</german>
      <japanese>ニ</japanese>
      <romaji>ni</romaji>
      <cat>Schriftzeichen</cat>
      <lection>Katakana</lection>
    </Vocabulary>
    <Vocabulary>
      <german>nu</german>
      <japanese>ヌ</japanese>
      <romaji>nu</romaji>
      <cat>Schriftzeichen</cat>
      <lection>Katakana</lection>
    </Vocabulary>
    <Vocabulary>
      <german>ne</german>
      <japanese>ネ</japanese>
      <romaji>ne</romaji>
      <cat>Schriftzeichen</cat>
      <lection>Katakana</lection>
    </Vocabulary>
    <Vocabulary>
      <german>no</german>
      <japanese>ノ</japanese>
      <romaji>no</romaji>
      <cat>Schriftzeichen</cat>
      <lection>Katakana</lection>
    </Vocabulary>
    <Vocabulary>
      <german>ha</german>
      <japanese>ハ</japanese>
      <romaji>ha</romaji>
      <cat>Schriftzeichen</cat>
      <lection>Katakana</lection>
    </Vocabulary>
    <Vocabulary>
      <german>hi</german>
      <japanese>ヒ</japanese>
      <romaji>hi</romaji>
      <cat>Schriftzeichen</cat>
      <lection>Katakana</lection>
    </Vocabulary>
    <Vocabulary>
      <german>fu</german>
      <japanese>フ</japanese>
      <romaji>fu</romaji>
      <cat>Schriftzeichen</cat>
      <lection>Katakana</lection>
    </Vocabulary>
    <Vocabulary>
      <german>he</german>
      <japanese>ヘ</japanese>
      <romaji>he</romaji>
      <cat>Schriftzeichen</cat>
      <lection>Katakana</lection>
    </Vocabulary>
    <Vocabulary>
      <german>ho</german>
      <japanese>ホ</japanese>
      <romaji>ho</romaji>
      <cat>Schriftzeichen</cat>
      <lection>Katakana</lection>
    </Vocabulary>
    <Vocabulary>
      <german>ma</german>
      <japanese>マ</japanese>
      <romaji>ma</romaji>
      <cat>Schriftzeichen</cat>
      <lection>Katakana</lection>
    </Vocabulary>
    <Vocabulary>
      <german>mi</german>
      <japanese>ミ</japanese>
      <romaji>mi</romaji>
      <cat>Schriftzeichen</cat>
      <lection>Katakana</lection>
    </Vocabulary>
    <Vocabulary>
      <german>mu</german>
      <japanese>ム</japanese>
      <romaji>mu</romaji>
      <cat>Schriftzeichen</cat>
      <lection>Katakana</lection>
    </Vocabulary>
    <Vocabulary>
      <german>me</german>
      <japanese>メ</japanese>
      <romaji>me</romaji>
      <cat>Schriftzeichen</cat>
      <lection>Katakana</lection>
    </Vocabulary>
    <Vocabulary>
      <german>mo</german>
      <japanese>モ</japanese>
      <romaji>mo</romaji>
      <cat>Schriftzeichen</cat>
      <lection>Katakana</lection>
    </Vocabulary>
    <Vocabulary>
      <german>yo</german>
      <japanese>ヨ</japanese>
      <romaji>yo</romaji>
      <cat>Schriftzeichen</cat>
      <lection>Katakana</lection>
    </Vocabulary>
    <Vocabulary>
      <german>yu</german>
      <japanese>ユ</japanese>
      <romaji>yu</romaji>
      <cat>Schriftzeichen</cat>
      <lection>Katakana</lection>
    </Vocabulary>
    <Vocabulary>
      <german>ya</german>
      <japanese>ヤ</japanese>
      <romaji>ya</romaji>
      <cat>Schriftzeichen</cat>
      <lection>Katakana</lection>
    </Vocabulary>
    <Vocabulary>
      <german>ra</german>
      <japanese>ラ</japanese>
      <romaji>ra</romaji>
      <cat>Schriftzeichen</cat>
      <lection>Katakana</lection>
    </Vocabulary>
    <Vocabulary>
      <german>ri</german>
      <japanese>リ</japanese>
      <romaji>ri</romaji>
      <cat>Schriftzeichen</cat>
      <lection>Katakana</lection>
    </Vocabulary>
    <Vocabulary>
      <german>ru</german>
      <japanese>ル</japanese>
      <romaji>ru</romaji>
      <cat>Schriftzeichen</cat>
      <lection>Katakana</lection>
    </Vocabulary>
    <Vocabulary>
      <german>re</german>
      <japanese>レ</japanese>
      <romaji>re</romaji>
      <cat>Schriftzeichen</cat>
      <lection>Katakana</lection>
    </Vocabulary>
    <Vocabulary>
      <german>ro</german>
      <japanese>ロ</japanese>
      <romaji>ro</romaji>
      <cat>Schriftzeichen</cat>
      <lection>Katakana</lection>
    </Vocabulary>
    <Vocabulary>
      <german>wa</german>
      <japanese>ワ</japanese>
      <romaji>wa</romaji>
      <cat>Schriftzeichen</cat>
      <lection>Katakana</lection>
    </Vocabulary>
    <Vocabulary>
      <german>wo</german>
      <japanese>ヲ</japanese>
      <romaji>wo</romaji>
      <cat>Schriftzeichen</cat>
      <lection>Katakana</lection>
    </Vocabulary>
    <Vocabulary>
      <german>n</german>
      <japanese>ン</japanese>
      <romaji>n</romaji>
      <cat>Schriftzeichen</cat>
      <lection>Katakana</lection>
    </Vocabulary>
    <Vocabulary>
      <german>Gericht</german>
      <japanese>りょうり</japanese>
      <romaji>ryoori</romaji>
      <cat>Nomen</cat>
      <lection>6</lection>
    </Vocabulary>
    <Vocabulary>
      <german>lieblings~</german>
      <japanese>すきな</japanese>
      <romaji>sukina</romaji>
      <cat>Präfix</cat>
      <lection>6</lection>
    </Vocabulary>
    <Vocabulary>
      <german>nicht gern</german>
      <japanese>きらいな</japanese>
      <romaji>kiraina</romaji>
      <cat>Präfix</cat>
      <lection>6</lection>
    </Vocabulary>
    <Vocabulary>
      <german>Geschäft</german>
      <japanese>みせ</japanese>
      <romaji>mise</romaji>
      <cat>Nomen</cat>
      <lection>6</lection>
    </Vocabulary>
    <Vocabulary>
      <german>lecker</german>
      <japanese>おいしい</japanese>
      <romaji>oishii</romaji>
      <cat>Adjektiv</cat>
      <lection>6</lection>
    </Vocabulary>
    <Vocabulary>
      <german>ekelhaft</german>
      <japanese>まずい</japanese>
      <romaji>mazui</romaji>
      <cat>Adjektiv</cat>
      <lection>6</lection>
    </Vocabulary>
    <Vocabulary>
      <german>teuer</german>
      <japanese>たかい</japanese>
      <romaji>takai</romaji>
      <cat>Adjektiv</cat>
      <lection>6</lection>
    </Vocabulary>
    <Vocabulary>
      <german>billig</german>
      <japanese>やすい</japanese>
      <romaji>yasui</romaji>
      <cat>Adjektiv</cat>
      <lection>6</lection>
    </Vocabulary>
    <Vocabulary>
      <german>schnell / früh</german>
      <japanese>はやい</japanese>
      <romaji>hayai</romaji>
      <cat>Adjektiv</cat>
      <lection>6</lection>
    </Vocabulary>
    <Vocabulary>
      <german>langsam / spät</german>
      <japanese>おそい</japanese>
      <romaji>osoi</romaji>
      <cat>Adjektiv</cat>
      <lection>6</lection>
    </Vocabulary>
    <Vocabulary>
      <german>ein Stück</german>
      <japanese>ひとつ</japanese>
      <romaji>hitotsu</romaji>
      <cat>Stückzahlen</cat>
      <lection>6</lection>
    </Vocabulary>
    <Vocabulary>
      <german>zwei Stück</german>
      <japanese>ふたつ</japanese>
      <romaji>futatsu</romaji>
      <cat>Stückzahlen</cat>
      <lection>6</lection>
    </Vocabulary>
    <Vocabulary>
      <german>drei Stück</german>
      <japanese>みっつ</japanese>
      <romaji>mittsu</romaji>
      <cat>Stückzahlen</cat>
      <lection>6</lection>
    </Vocabulary>
    <Vocabulary>
      <german>vier Stück</german>
      <japanese>よっつ</japanese>
      <romaji>yottsu</romaji>
      <cat>Stückzahlen</cat>
      <lection>6</lection>
    </Vocabulary>
    <Vocabulary>
      <german>fünf Stück</german>
      <japanese>いつつ</japanese>
      <romaji>itsutsu</romaji>
      <cat>Stückzahlen</cat>
      <lection>6</lection>
    </Vocabulary>
    <Vocabulary>
      <german>das Beste~</german>
      <japanese>いちばん</japanese>
      <romaji>ichiban</romaji>
      <cat>Präfix</cat>
      <lection>6</lection>
    </Vocabulary>
    <Vocabulary>
      <german>welcher Art</german>
      <japanese>どんな</japanese>
      <romaji>donna</romaji>
      <cat>Fragewörter</cat>
      <lection>6</lection>
    </Vocabulary>
    <Vocabulary>
      <german>machen sie~</german>
      <japanese>ください</japanese>
      <romaji>kudasai</romaji>
      <cat>Ausdruck</cat>
      <lection>6</lection>
    </Vocabulary>
    <Vocabulary>
      <german>Zeit</german>
      <japanese>じかん</japanese>
      <romaji>jikan</romaji>
      <cat>Nomen</cat>
      <lection>6</lection>
    </Vocabulary>
    <Vocabulary>
      <german>Geld</german>
      <japanese>おかね</japanese>
      <romaji>okane</romaji>
      <cat>Nomen</cat>
      <lection>6</lection>
    </Vocabulary>
    <Vocabulary>
      <german>Mitternacht</german>
      <japanese>れいじ</japanese>
      <romaji>reiji</romaji>
      <cat>Zeitwörter</cat>
      <lection>9</lection>
    </Vocabulary>
    <Vocabulary>
      <german>kommen</german>
      <japanese>来ます</japanese>
      <romaji>kimasu</romaji>
      <cat>Verben</cat>
      <lection>9</lection>
    </Vocabulary>
    <Vocabulary>
      <german>Buch</german>
      <japanese>本</japanese>
      <romaji>hon</romaji>
      <cat>Nomen</cat>
      <lection>9</lection>
    </Vocabulary>
    <Vocabulary>
      <german>immer</german>
      <japanese>いつも</japanese>
      <romaji>itsumo</romaji>
      <cat>Zeitwörter</cat>
      <lection>9</lection>
    </Vocabulary>
    <Vocabulary>
      <german>jetzt</german>
      <japanese>今</japanese>
      <romaji>ima</romaji>
      <cat>Zeitwörter</cat>
      <lection>9</lection>
    </Vocabulary>
    <Vocabulary>
      <german>vorgestern</german>
      <japanese>おととい</japanese>
      <romaji>ototoi</romaji>
      <cat>Zeitwörter</cat>
      <lection>10</lection>
    </Vocabulary>
    <Vocabulary>
      <german>übermorgen</german>
      <japanese>あさって</japanese>
      <romaji>asatte</romaji>
      <cat>Zeitwörter</cat>
      <lection>10</lection>
    </Vocabulary>
    <Vocabulary>
      <german>letzter Monat</german>
      <japanese>先月</japanese>
      <romaji>sengetsu</romaji>
      <cat>Zeitwörter</cat>
      <lection>10</lection>
    </Vocabulary>
    <Vocabulary>
      <german>dieser Monat</german>
      <japanese>今月</japanese>
      <romaji>kongetsu</romaji>
      <cat>Zeitwörter</cat>
      <lection>10</lection>
    </Vocabulary>
    <Vocabulary>
      <german>nächster Monat</german>
      <japanese>来月</japanese>
      <romaji>raigetsu</romaji>
      <cat>Zeitwörter</cat>
      <lection>10</lection>
    </Vocabulary>
    <Vocabulary>
      <german>letztes Jahr</german>
      <japanese>きょねん</japanese>
      <romaji>kyonen</romaji>
      <cat>Zeitwörter</cat>
      <lection>10</lection>
    </Vocabulary>
    <Vocabulary>
      <german>dieses Jahr</german>
      <japanese>ことし</japanese>
      <romaji>kotoshi</romaji>
      <cat>Zeitwörter</cat>
      <lection>10</lection>
    </Vocabulary>
    <Vocabulary>
      <german>nächstes Jahr</german>
      <japanese>らいねん</japanese>
      <romaji>rainen</romaji>
      <cat>Zeitwörter</cat>
      <lection>10</lection>
    </Vocabulary>
    <Vocabulary>
      <german>von ~ bis ~</german>
      <japanese>～から～まで</japanese>
      <romaji>~kara~made</romaji>
      <cat>Ausdruck</cat>
      <lection>10</lection>
    </Vocabulary>
    <Vocabulary>
      <german>Ferien / Pause</german>
      <japanese>休み</japanese>
      <romaji>yasumi</romaji>
      <cat>Nomen</cat>
      <lection>10</lection>
    </Vocabulary>
    <Vocabulary>
      <german>wie</german>
      <japanese>どう</japanese>
      <romaji>doo</romaji>
      <cat>Fragewörter</cat>
      <lection>10</lection>
    </Vocabulary>
    <Vocabulary>
      <german>Geburtstag</german>
      <japanese>たんじょうび</japanese>
      <romaji>tanjoobi</romaji>
      <cat>Nomen</cat>
      <lection>11</lection>
    </Vocabulary>
    <Vocabulary>
      <german>Song</german>
      <japanese>うた</japanese>
      <romaji>uta</romaji>
      <cat>Nomen</cat>
      <lection>11</lection>
    </Vocabulary>
    <Vocabulary>
      <german>singen</german>
      <japanese>うたいます</japanese>
      <romaji>utaimasu</romaji>
      <cat>Verben</cat>
      <lection>11</lection>
    </Vocabulary>
    <Vocabulary>
      <german>Lesen</german>
      <japanese>どくしょ</japanese>
      <romaji>dokusho</romaji>
      <cat>Nomen</cat>
      <lection>11</lection>
    </Vocabulary>
    <Vocabulary>
      <german>Novelle</german>
      <japanese>しょいせつ</japanese>
      <romaji>shoosetsu</romaji>
      <cat>Nomen</cat>
      <lection>11</lection>
    </Vocabulary>
    <Vocabulary>
      <german>Literatur</german>
      <japanese>ぶんがく</japanese>
      <romaji>bungaku</romaji>
      <cat>Nomen</cat>
      <lection>11</lection>
    </Vocabulary>
    <Vocabulary>
      <german>Magazin</german>
      <japanese>ざっし</japanese>
      <romaji>sasshi</romaji>
      <cat>Nomen</cat>
      <lection>11</lection>
    </Vocabulary>
    <Vocabulary>
      <german>Bild</german>
      <japanese>え</japanese>
      <romaji>e</romaji>
      <cat>Nomen</cat>
      <lection>11</lection>
    </Vocabulary>
    <Vocabulary>
      <german>Teezeremonie</german>
      <japanese>さどう</japanese>
      <romaji>sadoo</romaji>
      <cat>Nomen</cat>
      <lection>11</lection>
    </Vocabulary>
    <Vocabulary>
      <german>Gartenarbeit</german>
      <japanese>いけばな</japanese>
      <romaji>ikebana</romaji>
      <cat>Nomen</cat>
      <lection>11</lection>
    </Vocabulary>
    <Vocabulary>
      <german>entspannen</german>
      <japanese>ゆっくりします</japanese>
      <romaji>jukkuri-shimasu</romaji>
      <cat>Verben</cat>
      <lection>11</lection>
    </Vocabulary>
    <Vocabulary>
      <german>Veranstaltung</german>
      <japanese>イベント</japanese>
      <romaji>ibento</romaji>
      <cat>Nomen</cat>
      <lection>12</lection>
    </Vocabulary>
    <Vocabulary>
      <german>Spiel</german>
      <japanese>しあい</japanese>
      <romaji>shiai</romaji>
      <cat>Nomen</cat>
      <lection>12</lection>
    </Vocabulary>
    <Vocabulary>
      <german>Feuerwerk</german>
      <japanese>はなび</japanese>
      <romaji>hanabi</romaji>
      <cat>Nomen</cat>
      <lection>12</lection>
    </Vocabulary>
    <Vocabulary>
      <german>Feiertag</german>
      <japanese>しゅくじつ</japanese>
      <romaji>shukujitsu</romaji>
      <cat>Nomen</cat>
      <lection>12</lection>
    </Vocabulary>
    <Vocabulary>
      <german>Jahreszeit</german>
      <japanese>きせつ</japanese>
      <romaji>kisetsu</romaji>
      <cat>Nomen</cat>
      <lection>12</lection>
    </Vocabulary>
    <Vocabulary>
      <german>Frühling</german>
      <japanese>はる</japanese>
      <romaji>haru</romaji>
      <cat>Nomen</cat>
      <lection>12</lection>
    </Vocabulary>
    <Vocabulary>
      <german>Sommer</german>
      <japanese>なつ</japanese>
      <romaji>natsu</romaji>
      <cat>Nomen</cat>
      <lection>12</lection>
    </Vocabulary>
    <Vocabulary>
      <german>Herbst</german>
      <japanese>あき</japanese>
      <romaji>Herbst</romaji>
      <cat>Nomen</cat>
      <lection>12</lection>
    </Vocabulary>
    <Vocabulary>
      <german>Winter</german>
      <japanese>ふゆ</japanese>
      <romaji>fuyu</romaji>
      <cat>Nomen</cat>
      <lection>12</lection>
    </Vocabulary>
    <Vocabulary>
      <german>Stadt</german>
      <japanese>まち</japanese>
      <romaji>machi</romaji>
      <cat>Nomen</cat>
      <lection>12</lection>
    </Vocabulary>
    <Vocabulary>
      <german>zusammen</german>
      <japanese>いっしょ</japanese>
      <romaji>issho</romaji>
      <cat>Adverb</cat>
      <lection>12</lection>
    </Vocabulary>
    <Vocabulary>
      <german>nächstes mal</german>
      <japanese>こんど</japanese>
      <romaji>kondo</romaji>
      <cat>Zeitwörter</cat>
      <lection>12</lection>
    </Vocabulary>
    <Vocabulary>
      <german>noch einmal</german>
      <japanese>また</japanese>
      <romaji>mata</romaji>
      <cat>Adjektiv</cat>
      <lection>12</lection>
    </Vocabulary>
    <Vocabulary>
      <german>Das ist schade</german>
      <japanese>ざんねん　です</japanese>
      <romaji>zannen desu</romaji>
      <cat>Ausdruck</cat>
      <lection>12</lection>
    </Vocabulary>
    <Vocabulary>
      <german>Selbstverständlich</german>
      <japanese>もちろん</japanese>
      <romaji>mochiron</romaji>
      <cat>Ausdruck</cat>
      <lection>12</lection>
    </Vocabulary>
    <Vocabulary>
      <german>Ich freue mich drauf</german>
      <japanese>たのしみです</japanese>
      <romaji>tanoshimi desu</romaji>
      <cat>Ausdruck</cat>
      <lection>12</lection>
    </Vocabulary>
    <Vocabulary>
      <german>1</german>
      <japanese>一</japanese>
      <romaji>いち</romaji>
      <cat>Kanji</cat>
      <lection>Kanji</lection>
    </Vocabulary>
    <Vocabulary>
      <german>2</german>
      <japanese>二</japanese>
      <romaji>に</romaji>
      <cat>Kanji</cat>
      <lection>Kanji</lection>
    </Vocabulary>
    <Vocabulary>
      <german>3</german>
      <japanese>三</japanese>
      <romaji>さん</romaji>
      <cat>Kanji</cat>
      <lection>Kanji</lection>
    </Vocabulary>
    <Vocabulary>
      <german>4</german>
      <japanese>四</japanese>
      <romaji>よん</romaji>
      <cat>Kanji</cat>
      <lection>Kanji</lection>
    </Vocabulary>
    <Vocabulary>
      <german>5</german>
      <japanese>五</japanese>
      <romaji>ご</romaji>
      <cat>Kanji</cat>
      <lection>Kanji</lection>
    </Vocabulary>
    <Vocabulary>
      <german>6</german>
      <japanese>六</japanese>
      <romaji>ろく</romaji>
      <cat>Kanji</cat>
      <lection>Kanji</lection>
    </Vocabulary>
    <Vocabulary>
      <german>7</german>
      <japanese>七</japanese>
      <romaji>なな</romaji>
      <cat>Kanji</cat>
      <lection>Kanji</lection>
    </Vocabulary>
    <Vocabulary>
      <german>8</german>
      <japanese>八</japanese>
      <romaji>はち</romaji>
      <cat>Kanji</cat>
      <lection>Kanji</lection>
    </Vocabulary>
    <Vocabulary>
      <german>9</german>
      <japanese>九</japanese>
      <romaji>きゅう</romaji>
      <cat>Kanji</cat>
      <lection>Kanji</lection>
    </Vocabulary>
    <Vocabulary>
      <german>10</german>
      <japanese>十</japanese>
      <romaji>じゅう</romaji>
      <cat>Kanji</cat>
      <lection>Kanji</lection>
    </Vocabulary>
    <Vocabulary>
      <german>hell</german>
      <japanese>あかるい</japanese>
      <romaji>akarui</romaji>
      <cat>Adjektiv</cat>
      <lection>7</lection>
    </Vocabulary>
    <Vocabulary>
      <german>dunkel</german>
      <japanese>くらい</japanese>
      <romaji>kurai</romaji>
      <cat>Adjektiv</cat>
      <lection>7</lection>
    </Vocabulary>
    <Vocabulary>
      <german>neu</german>
      <japanese>あたらしい</japanese>
      <romaji>atarashii</romaji>
      <cat>Adjektiv</cat>
      <lection>7</lection>
    </Vocabulary>
    <Vocabulary>
      <german>alt</german>
      <japanese>ふるい</japanese>
      <romaji>furui</romaji>
      <cat>Adjektiv</cat>
      <lection>7</lection>
    </Vocabulary>
    <Vocabulary>
      <german>groß</german>
      <japanese>おおきい</japanese>
      <romaji>ookii</romaji>
      <cat>Adjektiv</cat>
      <lection>7</lection>
    </Vocabulary>
    <Vocabulary>
      <german>klein</german>
      <japanese>ちいさい</japanese>
      <romaji>chiisai</romaji>
      <cat>Adjektiv</cat>
      <lection>7</lection>
    </Vocabulary>
    <Vocabulary>
      <german>aufgeräumt/sauber</german>
      <japanese>きれい</japanese>
      <romaji>kiree</romaji>
      <cat>Adjektiv</cat>
      <lection>7</lection>
    </Vocabulary>
    <Vocabulary>
      <german>unaufgeräumt/dreckig</german>
      <japanese>きたない</japanese>
      <romaji>kitanai</romaji>
      <cat>Adjektiv</cat>
      <lection>7</lection>
    </Vocabulary>
    <Vocabulary>
      <german>groß/geräumig</german>
      <japanese>ひろい</japanese>
      <romaji>hiroi</romaji>
      <cat>Adjektiv</cat>
      <lection>7</lection>
    </Vocabulary>
    <Vocabulary>
      <german>klein/schmal</german>
      <japanese>せまい</japanese>
      <romaji>semai</romaji>
      <cat>Adjektiv</cat>
      <lection>7</lection>
    </Vocabulary>
    <Vocabulary>
      <german>toll/gut</german>
      <japanese>いい</japanese>
      <romaji>ii</romaji>
      <cat>Adjektiv</cat>
      <lection>7</lection>
    </Vocabulary>
    <Vocabulary>
      <german>arbeiten</german>
      <japanese>はたらきます</japanese>
      <romaji>hatarakimasu</romaji>
      <cat>Verben</cat>
      <lection>7</lection>
    </Vocabulary>
    <Vocabulary>
      <german>spieler/amüsieren</german>
      <japanese>あそびます</japanese>
      <romaji>asobimasu</romaji>
      <cat>Verben</cat>
      <lection>7</lection>
    </Vocabulary>
    <Vocabulary>
      <german>Reise</german>
      <japanese>りよこう</japanese>
      <romaji>riyokoo</romaji>
      <cat>Nomen</cat>
      <lection>7</lection>
    </Vocabulary>
    <Vocabulary>
      <german>Gesicht waschen</german>
      <japanese>かおを あらいます</japanese>
      <romaji>kao o araimasu</romaji>
      <cat>Verben</cat>
      <lection>9</lection>
    </Vocabulary>
    <Vocabulary>
      <german>Zähne putzen</german>
      <japanese>はを　みがきます</japanese>
      <romaji>ha o migakimasu</romaji>
      <cat>Verben</cat>
      <lection>9</lection>
    </Vocabulary>
    <Vocabulary>
      <german>Make up auftragen</german>
      <japanese>おけしょうを　します</japanese>
      <romaji>okeshoo o shimasu</romaji>
      <cat>Verben</cat>
      <lection>9</lection>
    </Vocabulary>
    <Vocabulary>
      <german>rasieren</german>
      <japanese>ひげを　そります</japanese>
      <romaji>hige o sorimasu</romaji>
      <cat>Verben</cat>
      <lection>9</lection>
    </Vocabulary>
    <Vocabulary>
      <german>sich anziehen</german>
      <japanese>ふくを　きます</japanese>
      <romaji>fuku o kimasu</romaji>
      <cat>Verben</cat>
      <lection>9</lection>
    </Vocabulary>
    <Vocabulary>
      <german>sich ausziehen</german>
      <japanese>ふくを　ぬぎます</japanese>
      <romaji>fuku o nugimasu</romaji>
      <cat>Verben</cat>
      <lection>9</lection>
    </Vocabulary>
    <Vocabulary>
      <german>Wäsche waschen</german>
      <japanese>せんたくを　します</japanese>
      <romaji>sentaku o shimasu</romaji>
      <cat>Verben</cat>
      <lection>9</lection>
    </Vocabulary>
    <Vocabulary>
      <german>Sonne</german>
      <japanese>日</japanese>
      <romaji>hi</romaji>
      <cat>Kanji</cat>
      <lection>Kanji</lection>
    </Vocabulary>
    <Vocabulary>
      <german>Anfang/Ursprung</german>
      <japanese>本</japanese>
      <romaji>もと</romaji>
      <cat>Kanji</cat>
      <lection>Kanji</lection>
    </Vocabulary>
    <Vocabulary>
      <german>Mensch</german>
      <japanese>人</japanese>
      <romaji>じん</romaji>
      <cat>Kanji</cat>
      <lection>Kanji</lection>
    </Vocabulary>
    <Vocabulary>
      <german>Wort</german>
      <japanese>語</japanese>
      <romaji>ご</romaji>
      <cat>Kanji</cat>
      <lection>Kanji</lection>
    </Vocabulary>
    <Vocabulary>
      <german>Kind</german>
      <japanese>子</japanese>
      <romaji>こ</romaji>
      <cat>Kanji</cat>
      <lection>Kanji</lection>
    </Vocabulary>
    <Vocabulary>
      <german>groß</german>
      <japanese>大</japanese>
      <romaji>おお</romaji>
      <cat>Kanji</cat>
      <lection>Kanji</lection>
    </Vocabulary>
    <Vocabulary>
      <german>Wissenschaft</german>
      <japanese>学</japanese>
      <romaji>がく</romaji>
      <cat>Kanji</cat>
      <lection>Kanji</lection>
    </Vocabulary>
    <Vocabulary>
      <german>früher</german>
      <japanese>先</japanese>
      <romaji>せん</romaji>
      <cat>Kanji</cat>
      <lection>Kanji</lection>
    </Vocabulary>
    <Vocabulary>
      <german>Leben</german>
      <japanese>生</japanese>
      <romaji>せい</romaji>
      <cat>Kanji</cat>
      <lection>Kanji</lection>
    </Vocabulary>
    <Vocabulary>
      <german>Ich</german>
      <japanese>私</japanese>
      <romaji>わたし</romaji>
      <cat>Kanji</cat>
      <lection>Kanji</lection>
    </Vocabulary>
    <Vocabulary>
      <german>Freund</german>
      <japanese>友</japanese>
      <romaji>とも</romaji>
      <cat>Kanji</cat>
      <lection>Kanji</lection>
    </Vocabulary>
    <Vocabulary>
      <german>was</german>
      <japanese>何</japanese>
      <romaji>nan</romaji>
      <cat>Kanji</cat>
      <lection>Kanji</lection>
    </Vocabulary>
    <Vocabulary>
      <german>Inneres</german>
      <japanese>中</japanese>
      <romaji>なか</romaji>
      <cat>Kanji</cat>
      <lection>Kanji</lection>
    </Vocabulary>
    <Vocabulary>
      <german>Land</german>
      <japanese>国</japanese>
      <romaji>くに</romaji>
      <cat>Kanji</cat>
      <lection>Kanji</lection>
    </Vocabulary>
    <Vocabulary>
      <german>100</german>
      <japanese>百</japanese>
      <romaji>ひゃく</romaji>
      <cat>Kanji</cat>
      <lection>Kanji</lection>
    </Vocabulary>
    <Vocabulary>
      <german>1000</german>
      <japanese>千</japanese>
      <romaji>せん</romaji>
      <cat>Kanji</cat>
      <lection>Kanji</lection>
    </Vocabulary>
    <Vocabulary>
      <german>10000</german>
      <japanese>万</japanese>
      <romaji>まん</romaji>
      <cat>Kanji</cat>
      <lection>Kanji</lection>
    </Vocabulary>
    <Vocabulary>
      <german>Yen</german>
      <japanese>円</japanese>
      <romaji>えん</romaji>
      <cat>Kanji</cat>
      <lection>Kanji</lection>
    </Vocabulary>
    <Vocabulary>
      <german>Jahr</german>
      <japanese>年</japanese>
      <romaji>ねん</romaji>
      <cat>Kanji</cat>
      <lection>Kanji</lection>
    </Vocabulary>
    <Vocabulary>
      <german>Mann</german>
      <japanese>男</japanese>
      <romaji>おとこ</romaji>
      <cat>Kanji</cat>
      <lection>Kanji</lection>
    </Vocabulary>
    <Vocabulary>
      <german>Frau</german>
      <japanese>女</japanese>
      <romaji>おんな</romaji>
      <cat>Kanji</cat>
      <lection>Kanji</lection>
    </Vocabulary>
    <Vocabulary>
      <german>Vater</german>
      <japanese>父</japanese>
      <romaji>ちち</romaji>
      <cat>Kanji</cat>
      <lection>Kanji</lection>
    </Vocabulary>
    <Vocabulary>
      <german>Mutter</german>
      <japanese>母</japanese>
      <romaji>はは</romaji>
      <cat>Kanji</cat>
      <lection>Kanji</lection>
    </Vocabulary>
    <Vocabulary>
      <german>Freundschaft</german>
      <japanese>好</japanese>
      <romaji>よしみ</romaji>
      <cat>Kanji</cat>
      <lection>Kanji</lection>
    </Vocabulary>
    <Vocabulary>
      <german>Fisch</german>
      <japanese>魚</japanese>
      <romaji>さかな</romaji>
      <cat>Kanji</cat>
      <lection>Kanji</lection>
    </Vocabulary>
    <Vocabulary>
      <german>Fleisch</german>
      <japanese>肉</japanese>
      <romaji>にく</romaji>
      <cat>Kanji</cat>
      <lection>Kanji</lection>
    </Vocabulary>
    <Vocabulary>
      <german>Eier</german>
      <japanese>卵</japanese>
      <romaji>たまご</romaji>
      <cat>Kanji</cat>
      <lection>Kanji</lection>
    </Vocabulary>
    <Vocabulary>
      <german>Wasser</german>
      <japanese>水</japanese>
      <romaji>みず</romaji>
      <cat>Kanji</cat>
      <lection>Kanji</lection>
    </Vocabulary>
    <Vocabulary>
      <german>Tee</german>
      <japanese>茶</japanese>
      <romaji>ちゃ</romaji>
      <cat>Kanji</cat>
      <lection>Kanji</lection>
    </Vocabulary>
    <Vocabulary>
      <german>Rind</german>
      <japanese>牛</japanese>
      <romaji>うし</romaji>
      <cat>Kanji</cat>
      <lection>Kanji</lection>
    </Vocabulary>
    <Vocabulary>
      <german>Gegenstand</german>
      <japanese>物</japanese>
      <romaji>もの</romaji>
      <cat>Kanji</cat>
      <lection>Kanji</lection>
    </Vocabulary>
    <Vocabulary>
      <german>Essen</german>
      <japanese>食</japanese>
      <romaji>しょく</romaji>
      <cat>Kanji</cat>
      <lection>Kanji</lection>
    </Vocabulary>
    <Vocabulary>
      <german>Trinken</german>
      <japanese>飲</japanese>
      <romaji>のみ</romaji>
      <cat>Kanji</cat>
      <lection>Kanji</lection>
    </Vocabulary>
    <Vocabulary>
      <german>Laden</german>
      <japanese>屋</japanese>
      <romaji>や</romaji>
      <cat>Kanji</cat>
      <lection>Kanji</lection>
    </Vocabulary>
    <Vocabulary>
      <german>jeden</german>
      <japanese>毎</japanese>
      <romaji>まい</romaji>
      <cat>Kanji</cat>
      <lection>Kanji</lection>
    </Vocabulary>
    <Vocabulary>
      <german>Zeit</german>
      <japanese>時</japanese>
      <romaji>とき</romaji>
      <cat>Kanji</cat>
      <lection>Kanji</lection>
    </Vocabulary>
    <Vocabulary>
      <german>gehen</german>
      <japanese>行</japanese>
      <romaji>こう</romaji>
      <cat>Kanji</cat>
      <lection>Kanji</lection>
    </Vocabulary>
    <Vocabulary>
      <german>nächstes</german>
      <japanese>来</japanese>
      <romaji>らい</romaji>
      <cat>Kanji</cat>
      <lection>Kanji</lection>
    </Vocabulary>
    <Vocabulary>
      <german>Mond</german>
      <japanese>月</japanese>
      <romaji>がつ</romaji>
      <cat>Kanji</cat>
      <lection>Kanji</lection>
    </Vocabulary>
    <Vocabulary>
      <german>Feuer</german>
      <japanese>火</japanese>
      <romaji>ひ</romaji>
      <cat>Kanji</cat>
      <lection>Kanji</lection>
    </Vocabulary>
    <Vocabulary>
      <german>Baum</german>
      <japanese>木</japanese>
      <romaji>き</romaji>
      <cat>Kanji</cat>
      <lection>Kanji</lection>
    </Vocabulary>
    <Vocabulary>
      <german>Gold</german>
      <japanese>金</japanese>
      <romaji>こがね</romaji>
      <cat>Kanji</cat>
      <lection>Kanji</lection>
    </Vocabulary>
    <Vocabulary>
      <german>Erde</german>
      <japanese>土</japanese>
      <romaji>と</romaji>
      <cat>Kanji</cat>
      <lection>Kanji</lection>
    </Vocabulary>
    <Vocabulary>
      <german>Student</german>
      <japanese>学生</japanese>
      <romaji>がくせい</romaji>
      <cat>Kanji</cat>
      <lection>Kanji</lection>
    </Vocabulary>
    <Vocabulary>
      <german>Universität</german>
      <japanese>大学</japanese>
      <romaji>だいがく</romaji>
      <cat>Kanji</cat>
      <lection>Kanji</lection>
    </Vocabulary>
    <Vocabulary>
      <german>Lehrer</german>
      <japanese>先生</japanese>
      <romaji>せんせい</romaji>
      <cat>Kanji</cat>
      <lection>Kanji</lection>
    </Vocabulary>
    <Vocabulary>
      <german>China</german>
      <japanese>中国</japanese>
      <romaji>ちゅうごく</romaji>
      <cat>Kanji</cat>
      <lection>Kanji</lection>
    </Vocabulary>
    <Vocabulary>
      <german>Familie</german>
      <japanese>家族</japanese>
      <romaji>かぞく</romaji>
      <cat>Kanji</cat>
      <lection>Kanji</lection>
    </Vocabulary>
    <Vocabulary>
      <german>Junge</german>
      <japanese>男の子</japanese>
      <romaji>おとこのこ</romaji>
      <cat>Kanji</cat>
      <lection>Kanji</lection>
    </Vocabulary>
    <Vocabulary>
      <german>Mädchen</german>
      <japanese>女の子</japanese>
      <romaji>おんなのこ</romaji>
      <cat>Kanji</cat>
      <lection>Kanji</lection>
    </Vocabulary>
    <Vocabulary>
      <german>jeden Tag</german>
      <japanese>毎日</japanese>
      <romaji>まいにち</romaji>
      <cat>Kanji</cat>
      <lection>Kanji</lection>
    </Vocabulary>
    <Vocabulary>
      <german>heute</german>
      <japanese>今日</japanese>
      <romaji>きょう</romaji>
      <cat>Kanji</cat>
      <lection>Kanji</lection>
    </Vocabulary>
    <Vocabulary>
      <german>Woche</german>
      <japanese>週</japanese>
      <romaji>しゅう</romaji>
      <cat>Kanji</cat>
      <lection>Kanji</lection>
    </Vocabulary>
    <Vocabulary>
      <german>letzte Woche</german>
      <japanese>先週</japanese>
      <romaji>せんしゅう</romaji>
      <cat>Kanji</cat>
      <lection>Kanji</lection>
    </Vocabulary>
    <Vocabulary>
      <german>diese Woche</german>
      <japanese>今週</japanese>
      <romaji>こんしゅう</romaji>
      <cat>Kanji</cat>
      <lection>Kanji</lection>
    </Vocabulary>
    <Vocabulary>
      <german>nächste Woche</german>
      <japanese>来週</japanese>
      <romaji>らいしゅう</romaji>
      <cat>Kanji</cat>
      <lection>Kanji</lection>
    </Vocabulary>
    <Vocabulary>
      <german>Wochenende</german>
      <japanese>週末</japanese>
      <romaji>しゅうまつ</romaji>
      <cat>Kanji</cat>
      <lection>Kanji</lection>
    </Vocabulary>
    <Vocabulary>
      <german>gestern</german>
      <japanese>昨日</japanese>
      <romaji>きのう</romaji>
      <cat>Kanji</cat>
      <lection>Kanji</lection>
    </Vocabulary>
    <Vocabulary>
      <german>morgen</german>
      <japanese>明日</japanese>
      <romaji>あした</romaji>
      <cat>Kanji</cat>
      <lection>Kanji</lection>
    </Vocabulary>
    <Vocabulary>
      <german>neu</german>
      <japanese>新</japanese>
      <romaji>さら</romaji>
      <cat>Kanji</cat>
      <lection>Kanji</lection>
    </Vocabulary>
    <Vocabulary>
      <german>neu</german>
      <japanese>新しい</japanese>
      <romaji>あたらし</romaji>
      <cat>Kanji</cat>
      <lection>Kanji</lection>
    </Vocabulary>
    <Vocabulary>
      <german>alt</german>
      <japanese>古</japanese>
      <romaji>ふる</romaji>
      <cat>Kanji</cat>
      <lection>Kanji</lection>
    </Vocabulary>
    <Vocabulary>
      <german>alt</german>
      <japanese>古い</japanese>
      <romaji>ふるい</romaji>
      <cat>Kanji</cat>
      <lection>Kanji</lection>
    </Vocabulary>
    <Vocabulary>
      <german>hell</german>
      <japanese>明</japanese>
      <romaji>さや</romaji>
      <cat>Kanji</cat>
      <lection>Kanji</lection>
    </Vocabulary>
    <Vocabulary>
      <german>hell</german>
      <japanese>明い</japanese>
      <romaji>あかるい</romaji>
      <cat>Kanji</cat>
      <lection>Kanji</lection>
    </Vocabulary>
    <Vocabulary>
      <german>dunkel</german>
      <japanese>暗い</japanese>
      <romaji>くらい</romaji>
      <cat>Kanji</cat>
      <lection>Kanji</lection>
    </Vocabulary>
    <Vocabulary>
      <german>Höhe</german>
      <japanese>高</japanese>
      <romaji>たか</romaji>
      <cat>Kanji</cat>
      <lection>Kanji</lection>
    </Vocabulary>
    <Vocabulary>
      <german>teuer</german>
      <japanese>高い</japanese>
      <romaji>たかい</romaji>
      <cat>Kanji</cat>
      <lection>Kanji</lection>
    </Vocabulary>
    <Vocabulary>
      <german>billig</german>
      <japanese>安</japanese>
      <romaji>やす</romaji>
      <cat>Kanji</cat>
      <lection>Kanji</lection>
    </Vocabulary>
    <Vocabulary>
      <german>billig</german>
      <japanese>安い</japanese>
      <romaji>やすい</romaji>
      <cat>Kanji</cat>
      <lection>Kanji</lection>
    </Vocabulary>
    <Vocabulary>
      <german>Behaglichkeit</german>
      <japanese>楽</japanese>
      <romaji>らく</romaji>
      <cat>Kanji</cat>
      <lection>Kanji</lection>
    </Vocabulary>
    <Vocabulary>
      <german>lustig</german>
      <japanese>楽しい</japanese>
      <romaji>たのしい</romaji>
      <cat>Kanji</cat>
      <lection>Kanji</lection>
    </Vocabulary>
    <Vocabulary>
      <german>weiß</german>
      <japanese>白い</japanese>
      <romaji>しろい</romaji>
      <cat>Kanji</cat>
      <lection>Kanji</lection>
    </Vocabulary>
    <Vocabulary>
      <german>schwarz</german>
      <japanese>黒い</japanese>
      <romaji>くろい</romaji>
      <cat>Kanji</cat>
      <lection>Kanji</lection>
    </Vocabulary>
    <Vocabulary>
      <german>rot</german>
      <japanese>赤い</japanese>
      <romaji>あかい</romaji>
      <cat>Kanji</cat>
      <lection>Kanji</lection>
    </Vocabulary>
    <Vocabulary>
      <german>blau</german>
      <japanese>青い</japanese>
      <romaji>あおい</romaji>
      <cat>Kanji</cat>
      <lection>Kanji</lection>
    </Vocabulary>
    <Vocabulary>
      <german>Haus</german>
      <japanese>家</japanese>
      <romaji>いえ</romaji>
      <cat>Kanji</cat>
      <lection>Kanji</lection>
    </Vocabulary>
    <Vocabulary>
      <german>Anfang/Ursprung</german>
      <japanese>元</japanese>
      <romaji>もと</romaji>
      <cat>Kanji</cat>
      <lection>Kanji</lection>
    </Vocabulary>
    <Vocabulary>
      <german>Geist</german>
      <japanese>気</japanese>
      <romaji>き</romaji>
      <cat>Kanji</cat>
      <lection>Kanji</lection>
    </Vocabulary>
    <Vocabulary>
      <german>Sein</german>
      <japanese>有</japanese>
      <romaji>ゆう</romaji>
      <cat>Kanji</cat>
      <lection>Kanji</lection>
    </Vocabulary>
    <Vocabulary>
      <german>Name</german>
      <japanese>名</japanese>
      <romaji>な</romaji>
      <cat>Kanji</cat>
      <lection>Kanji</lection>
    </Vocabulary>
    <Vocabulary>
      <german>Hund</german>
      <japanese>犬</japanese>
      <romaji>いぬ</romaji>
      <cat>Kanji</cat>
      <lection>Kanji</lection>
    </Vocabulary>
    <Vocabulary>
      <german>gesund</german>
      <japanese>元気</japanese>
      <romaji>げんき</romaji>
      <cat>Kanji</cat>
      <lection>Kanji</lection>
    </Vocabulary>
    <Vocabulary>
      <german>berühmt</german>
      <japanese>有名</japanese>
      <romaji>ゆうめ</romaji>
      <cat>Kanji</cat>
      <lection>Kanji</lection>
    </Vocabulary>
    <Vocabulary>
      <german>Musik</german>
      <japanese>音楽</japanese>
      <romaji>おんがく</romaji>
      <cat>Kanji</cat>
      <lection>Kanji</lection>
    </Vocabulary>
    <Vocabulary>
      <german>Geräusch</german>
      <japanese>音</japanese>
      <romaji>おん</romaji>
      <cat>Kanji</cat>
      <lection>Kanji</lection>
    </Vocabulary>
    <Vocabulary>
      <german>Auge</german>
      <japanese>目</japanese>
      <romaji>め</romaji>
      <cat>Kanji</cat>
      <lection>Kanji</lection>
    </Vocabulary>
    <Vocabulary>
      <german>Mund/Tor</german>
      <japanese>口</japanese>
      <romaji>くち</romaji>
      <cat>Kanji</cat>
      <lection>Kanji</lection>
    </Vocabulary>
    <Vocabulary>
      <german>Ohr</german>
      <japanese>耳</japanese>
      <romaji>みみ</romaji>
      <cat>Kanji</cat>
      <lection>Kanji</lection>
    </Vocabulary>
    <Vocabulary>
      <german>Hand</german>
      <japanese>手</japanese>
      <romaji>て</romaji>
      <cat>Kanji</cat>
      <lection>Kanji</lection>
    </Vocabulary>
    <Vocabulary>
      <german>Fuß/Bein</german>
      <japanese>足</japanese>
      <romaji>あし</romaji>
      <cat>Kanji</cat>
      <lection>Kanji</lection>
    </Vocabulary>
    <Vocabulary>
      <german>Schauen</german>
      <japanese>見</japanese>
      <romaji>み</romaji>
      <cat>Kanji</cat>
      <lection>Kanji</lection>
    </Vocabulary>
    <Vocabulary>
      <german>Tor</german>
      <japanese>門</japanese>
      <romaji>かど</romaji>
      <cat>Kanji</cat>
      <lection>Kanji</lection>
    </Vocabulary>
    <Vocabulary>
      <german>treffen</german>
      <japanese>会います</japanese>
      <romaji>あいます</romaji>
      <cat>Kanji</cat>
      <lection>Kanji</lection>
    </Vocabulary>
    <Vocabulary>
      <german>kaufen</german>
      <japanese>買います</japanese>
      <romaji>かいます</romaji>
      <cat>Kanji</cat>
      <lection>Kanji</lection>
    </Vocabulary>
    <Vocabulary>
      <german>Lesen</german>
      <japanese>読書</japanese>
      <romaji>どくしょ</romaji>
      <cat>Kanji</cat>
      <lection>Kanji</lection>
    </Vocabulary>
    <Vocabulary>
      <german>hinausgehen</german>
      <japanese>出ます</japanese>
      <romaji>でます</romaji>
      <cat>Kanji</cat>
      <lection>Kanji</lection>
    </Vocabulary>
    <Vocabulary>
      <german>herausholen</german>
      <japanese>出します</japanese>
      <romaji>だします</romaji>
      <cat>Kanji</cat>
      <lection>Kanji</lection>
    </Vocabulary>
    <Vocabulary>
      <german>Eingang</german>
      <japanese>入口</japanese>
      <romaji>いりぐち</romaji>
      <cat>Kanji</cat>
      <lection>Kanji</lection>
    </Vocabulary>
    <Vocabulary>
      <german>Ausgang</german>
      <japanese>出口</japanese>
      <romaji>でぐち</romaji>
      <cat>Kanji</cat>
      <lection>Kanji</lection>
    </Vocabulary>
    <Vocabulary>
      <german>oben</german>
      <japanese>上</japanese>
      <romaji>うえ</romaji>
      <cat>Kanji</cat>
      <lection>Kanji</lection>
    </Vocabulary>
    <Vocabulary>
      <german>unten</german>
      <japanese>下</japanese>
      <romaji>した</romaji>
      <cat>Kanji</cat>
      <lection>Kanji</lection>
    </Vocabulary>
    <Vocabulary>
      <german>vorne</german>
      <japanese>前</japanese>
      <romaji>まえ</romaji>
      <cat>Kanji</cat>
      <lection>Kanji</lection>
    </Vocabulary>
    <Vocabulary>
      <german>hinten</german>
      <japanese>後</japanese>
      <romaji>うしろ</romaji>
      <cat>Kanji</cat>
      <lection>Kanji</lection>
    </Vocabulary>
    <Vocabulary>
      <german>rechts</german>
      <japanese>右</japanese>
      <romaji>みぎ</romaji>
      <cat>Kanji</cat>
      <lection>Kanji</lection>
    </Vocabulary>
    <Vocabulary>
      <german>links</german>
      <japanese>左</japanese>
      <romaji>ひだり</romaji>
      <cat>Kanji</cat>
      <lection>Kanji</lection>
    </Vocabulary>
    <Vocabulary>
      <german>Außengebiet</german>
      <japanese>外</japanese>
      <romaji>そと</romaji>
      <cat>Kanji</cat>
      <lection>Kanji</lection>
    </Vocabulary>
    <Vocabulary>
      <german>Zwischenraum</german>
      <japanese>間</japanese>
      <romaji>あいだ</romaji>
      <cat>Kanji</cat>
      <lection>Kanji</lection>
    </Vocabulary>
    <Vocabulary>
      <german>nah</german>
      <japanese>近い</japanese>
      <romaji>ちかい</romaji>
      <cat>Kanji</cat>
      <lection>Kanji</lection>
    </Vocabulary>
    <Vocabulary>
      <german>Pferd</german>
      <japanese>午</japanese>
      <romaji>うま</romaji>
      <cat>Kanji</cat>
      <lection>Kanji</lection>
    </Vocabulary>
    <Vocabulary>
      <german>Auto</german>
      <japanese>車</japanese>
      <romaji>くるま</romaji>
      <cat>Kanji</cat>
      <lection>Kanji</lection>
    </Vocabulary>
    <Vocabulary>
      <german>selbst</german>
      <japanese>自</japanese>
      <romaji>じ</romaji>
      <cat>Kanji</cat>
      <lection>Kanji</lection>
    </Vocabulary>
    <Vocabulary>
      <german>herumdrehen</german>
      <japanese>転</japanese>
      <romaji>てん</romaji>
      <cat>Kanji</cat>
      <lection>Kanji</lection>
    </Vocabulary>
    <Vocabulary>
      <german>Bahnhof</german>
      <japanese>駅</japanese>
      <romaji>えき</romaji>
      <cat>Kanji</cat>
      <lection>Kanji</lection>
    </Vocabulary>
    <Vocabulary>
      <german>Erde</german>
      <japanese>地</japanese>
      <romaji>ち</romaji>
      <cat>Kanji</cat>
      <lection>Kanji</lection>
    </Vocabulary>
    <Vocabulary>
      <german>Eisen</german>
      <japanese>鉄</japanese>
      <romaji>くろがね</romaji>
      <cat>Kanji</cat>
      <lection>Kanji</lection>
    </Vocabulary>
    <Vocabulary>
      <german>Osten</german>
      <japanese>東</japanese>
      <romaji>ひがし</romaji>
      <cat>Kanji</cat>
      <lection>Kanji</lection>
    </Vocabulary>
    <Vocabulary>
      <german>Westen</german>
      <japanese>西</japanese>
      <romaji>にし</romaji>
      <cat>Kanji</cat>
      <lection>Kanji</lection>
    </Vocabulary>
    <Vocabulary>
      <german>Süden</german>
      <japanese>南</japanese>
      <romaji>みなみ</romaji>
      <cat>Kanji</cat>
      <lection>Kanji</lection>
    </Vocabulary>
    <Vocabulary>
      <german>Norden</german>
      <japanese>北</japanese>
      <romaji>きた</romaji>
      <cat>Kanji</cat>
      <lection>Kanji</lection>
    </Vocabulary>
    <Vocabulary>
      <german>Stadt</german>
      <japanese>町</japanese>
      <romaji>まち</romaji>
      <cat>Kanji</cat>
      <lection>Kanji</lection>
    </Vocabulary>
    <Vocabulary>
      <german>Fahrrad</german>
      <japanese>自転車</japanese>
      <romaji>じてんしゃ</romaji>
      <cat>Kanji</cat>
      <lection>Kanji</lection>
    </Vocabulary>
    <Vocabulary>
      <german>Zug</german>
      <japanese>電車</japanese>
      <romaji>でんしゃ</romaji>
      <cat>Kanji</cat>
      <lection>Kanji</lection>
    </Vocabulary>
    <Vocabulary>
      <german>U-Bahn</german>
      <japanese>地下鉄</japanese>
      <romaji>ちかてつ</romaji>
      <cat>Kanji</cat>
      <lection>Kanji</lection>
    </Vocabulary>
    <Vocabulary>
      <german>Himmel</german>
      <japanese>天</japanese>
      <romaji>てん</romaji>
      <cat>Kanji</cat>
      <lection>Kanji</lection>
    </Vocabulary>
    <Vocabulary>
      <german>Regen</german>
      <japanese>雨</japanese>
      <romaji>あめ</romaji>
      <cat>Kanji</cat>
      <lection>Kanji</lection>
    </Vocabulary>
    <Vocabulary>
      <german>Schnee</german>
      <japanese>雪</japanese>
      <romaji>ゆき</romaji>
      <cat>Kanji</cat>
      <lection>Kanji</lection>
    </Vocabulary>
    <Vocabulary>
      <german>Wolke</german>
      <japanese>雲</japanese>
      <romaji>くも</romaji>
      <cat>Kanji</cat>
      <lection>Kanji</lection>
    </Vocabulary>
    <Vocabulary>
      <german>Telefon</german>
      <japanese>電話</japanese>
      <romaji>でんわ</romaji>
      <cat>Kanji</cat>
      <lection>Kanji</lection>
    </Vocabulary>
	    <Vocabulary>
      <german>einschalten</german>
      <japanese>つける</japanese>
      <romaji>tsukemasu</romaji>
      <cat>Verben</cat>
      <lection>14</lection>
    </Vocabulary>
    <Vocabulary>
      <german>ausschalten</german>
      <japanese>けす</japanese>
      <romaji />
      <cat>Verben</cat>
      <lection>14</lection>
    </Vocabulary>
    <Vocabulary>
      <german>öffnen</german>
      <japanese>あける</japanese>
      <romaji>開ける</romaji>
      <cat>Verben</cat>
      <lection>14</lection>
    </Vocabulary>
    <Vocabulary>
      <german>schließen</german>
      <japanese>しめる</japanese>
      <romaji>閉める</romaji>
      <cat>Verben</cat>
      <lection>14</lection>
    </Vocabulary>
    <Vocabulary>
      <german>sich beeilen</german>
      <japanese>いそぐ</japanese>
      <romaji>急ぐ</romaji>
      <cat>Verben</cat>
      <lection>14</lection>
    </Vocabulary>
    <Vocabulary>
      <german>warten</german>
      <japanese>まつ</japanese>
      <romaji>待つ</romaji>
      <cat>Verben</cat>
      <lection>14</lection>
    </Vocabulary>
    <Vocabulary>
      <german>tragen, besitzen</german>
      <japanese>もつ</japanese>
      <romaji>持つ</romaji>
      <cat>Verben</cat>
      <lection>14</lection>
    </Vocabulary>
    <Vocabulary>
      <german>nehmen</german>
      <japanese>とる</japanese>
      <romaji>取る</romaji>
      <cat>Verben</cat>
      <lection>14</lection>
    </Vocabulary>
    <Vocabulary>
      <german>helfen</german>
      <japanese>てつだう</japanese>
      <romaji>手伝う</romaji>
      <cat>Verben</cat>
      <lection>14</lection>
    </Vocabulary>
    <Vocabulary>
      <german>rufen</german>
      <japanese>よぶ</japanese>
      <romaji>呼ぶ</romaji>
      <cat>Verben</cat>
      <lection>14</lection>
    </Vocabulary>
    <Vocabulary>
      <german>benutzen</german>
      <japanese>つかう</japanese>
      <romaji>使う</romaji>
      <cat>Verben</cat>
      <lection>14</lection>
    </Vocabulary>
    <Vocabulary>
      <german>parken, anhalten</german>
      <japanese>とめる</japanese>
      <romaji>止める</romaji>
      <cat>Verben</cat>
      <lection>14</lection>
    </Vocabulary>
    <Vocabulary>
      <german>zeigen</german>
      <japanese>みせる</japanese>
      <romaji>見せる</romaji>
      <cat>Verben</cat>
      <lection>14</lection>
    </Vocabulary>
    <Vocabulary>
      <german>erklären</german>
      <japanese>おしえる</japanese>
      <romaji>教える</romaji>
      <cat>Verben</cat>
      <lection>14</lection>
    </Vocabulary>
    <Vocabulary>
      <german>setzen</german>
      <japanese>すわる</japanese>
      <romaji>座る</romaji>
      <cat>Verben</cat>
      <lection>14</lection>
    </Vocabulary>
    <Vocabulary>
      <german>hinstellen</german>
      <japanese>たつ</japanese>
      <romaji>立つ</romaji>
      <cat>Verben</cat>
      <lection>14</lection>
    </Vocabulary>
    <Vocabulary>
      <german>hineingehen</german>
      <japanese>はいる</japanese>
      <romaji>入る</romaji>
      <cat>Verben</cat>
      <lection>14</lection>
    </Vocabulary>
    <Vocabulary>
      <german>herausgehen</german>
      <japanese>だす</japanese>
      <romaji>出す</romaji>
      <cat>Verben</cat>
      <lection>14</lection>
    </Vocabulary>
    <Vocabulary>
      <german>fallen</german>
      <japanese>ふる</japanese>
      <romaji>降る</romaji>
      <cat>Verben</cat>
      <lection>14</lection>
    </Vocabulary>
    <Vocabulary>
      <german>Elektrizität</german>
      <japanese>でんき</japanese>
      <romaji>電気</romaji>
      <cat>Nomen</cat>
      <lection>14</lection>
    </Vocabulary>
    <Vocabulary>
      <german>Adresse</german>
      <japanese>じゅうしょ</japanese>
      <romaji>住所</romaji>
      <cat>Nomen</cat>
      <lection>14</lection>
    </Vocabulary>
    <Vocabulary>
      <german>Salz</german>
      <japanese>しお</japanese>
      <romaji>塩</romaji>
      <cat>Nomen</cat>
      <lection>14</lection>
    </Vocabulary>
    <Vocabulary>
      <german>Frage</german>
      <japanese>もんだい</japanese>
      <romaji>問題</romaji>
      <cat>Nomen</cat>
      <lection>14</lection>
    </Vocabulary>
    <Vocabulary>
      <german>Antwort</german>
      <japanese>こたえ</japanese>
      <romaji>答え</romaji>
      <cat>Nomen</cat>
      <lection>14</lection>
    </Vocabulary>
    <Vocabulary>
      <german>sofort</german>
      <japanese>すぐ</japanese>
      <romaji />
      <cat>Adverb</cat>
      <lection>14</lection>
    </Vocabulary>
    <Vocabulary>
      <german>später</german>
      <japanese>あとで</japanese>
      <romaji />
      <cat>Adverb</cat>
      <lection>14</lection>
    </Vocabulary>
    <Vocabulary>
      <german>ein bisschen mehr</german>
      <japanese>もうすこし</japanese>
      <romaji>もう少し</romaji>
      <cat>Ausdruck</cat>
      <lection>14</lection>
    </Vocabulary>
    <Vocabulary>
      <german>Wechselgeld</german>
      <japanese>おつり</japanese>
      <romaji>お釣り</romaji>
      <cat>Nomen</cat>
      <lection>14</lection>
    </Vocabulary>
    <Vocabulary>
      <german>stellen, legen</german>
      <japanese>おく</japanese>
      <romaji>置く</romaji>
      <cat>Verben</cat>
      <lection>15</lection>
    </Vocabulary>
    <Vocabulary>
      <german>herstellen</german>
      <japanese>つくる</japanese>
      <romaji>作る</romaji>
      <cat>Verben</cat>
      <lection>15</lection>
    </Vocabulary>
    <Vocabulary>
      <german>verkaufen</german>
      <japanese>うる</japanese>
      <romaji>売る</romaji>
      <cat>Verben</cat>
      <lection>15</lection>
    </Vocabulary>
    <Vocabulary>
      <german>kennen lernen</german>
      <japanese>しる</japanese>
      <romaji>知る</romaji>
      <cat>Verben</cat>
      <lection>15</lection>
    </Vocabulary>
    <Vocabulary>
      <german>wohnen</german>
      <japanese>すむ</japanese>
      <romaji>住む</romaji>
      <cat>Verben</cat>
      <lection>15</lection>
    </Vocabulary>
    <Vocabulary>
      <german>forschen</german>
      <japanese>けんきゅうする</japanese>
      <romaji>研究する</romaji>
      <cat>Verben</cat>
      <lection>15</lection>
    </Vocabulary>
    <Vocabulary>
      <german>Material, Daten</german>
      <japanese>しりょう</japanese>
      <romaji>資料</romaji>
      <cat>Nomen</cat>
      <lection>15</lection>
    </Vocabulary>
    <Vocabulary>
      <german>Fahrplan</german>
      <japanese>じこくひょう</japanese>
      <romaji>時刻表</romaji>
      <cat>Nomen</cat>
      <lection>15</lection>
    </Vocabulary>
    <Vocabulary>
      <german>Kleidung</german>
      <japanese>ふく</japanese>
      <romaji>服</romaji>
      <cat>Nomen</cat>
      <lection>15</lection>
    </Vocabulary>
    <Vocabulary>
      <german>Produkt</german>
      <japanese>せいひん</japanese>
      <romaji>製品</romaji>
      <cat>Nomen</cat>
      <lection>15</lection>
    </Vocabulary>
    <Vocabulary>
      <german>Wirtschaft</german>
      <japanese>けいざい</japanese>
      <romaji>経済</romaji>
      <cat>Nomen</cat>
      <lection>15</lection>
    </Vocabulary>
    <Vocabulary>
      <german>Rathaus</german>
      <japanese>しやくしょ</japanese>
      <romaji>市役所</romaji>
      <cat>Nomen</cat>
      <lection>15</lection>
    </Vocabulary>
    <Vocabulary>
      <german>Oberschule</german>
      <japanese>こうこう</japanese>
      <romaji>高校</romaji>
      <cat>Nomen</cat>
      <lection>15</lection>
    </Vocabulary>
    <Vocabulary>
      <german>Zahnarzt</german>
      <japanese>はいしゃ</japanese>
      <romaji>はいしゃ</romaji>
      <cat>Nomen</cat>
      <lection>15</lection>
    </Vocabulary>
    <Vocabulary>
      <german>ledig</german>
      <japanese>どくしん</japanese>
      <romaji>独身</romaji>
      <cat>Adjektiv</cat>
      <lection>15</lection>
    </Vocabulary>
    <Vocabulary>
      <german>sich erinnern</german>
      <japanese>おもいだす</japanese>
      <romaji>思い出す</romaji>
      <cat>Verben</cat>
      <lection>15</lection>
    </Vocabulary>
    <Vocabulary>
      <german>fahren</german>
      <japanese>のる</japanese>
      <romaji>乗る</romaji>
      <cat>Verben</cat>
      <lection>16</lection>
    </Vocabulary>
    <Vocabulary>
      <german>aussteigen</german>
      <japanese>おりる</japanese>
      <romaji>降りる</romaji>
      <cat>Verben</cat>
      <lection>16</lection>
    </Vocabulary>
    <Vocabulary>
      <german>umsteigen</german>
      <japanese>のりかえる</japanese>
      <romaji>乗り換える</romaji>
      <cat>Verben</cat>
      <lection>16</lection>
    </Vocabulary>
    <Vocabulary>
      <german>duschen</german>
      <japanese>あびる</japanese>
      <romaji>浴びる</romaji>
      <cat>Verben</cat>
      <lection>16</lection>
    </Vocabulary>
    <Vocabulary>
      <german>hineintun</german>
      <japanese>いれる</japanese>
      <romaji>入れる</romaji>
      <cat>Verben</cat>
      <lection>16</lection>
    </Vocabulary>
    <Vocabulary>
      <german>abheben</german>
      <japanese>おろす</japanese>
      <romaji>下ろす</romaji>
      <cat>Verben</cat>
      <lection>16</lection>
    </Vocabulary>
    <Vocabulary>
      <german>schieben, drücken</german>
      <japanese>おす</japanese>
      <romaji>押す</romaji>
      <cat>Verben</cat>
      <lection>16</lection>
    </Vocabulary>
    <Vocabulary>
      <german>anfangen</german>
      <japanese>はじめる</japanese>
      <romaji>始める</romaji>
      <cat>Verben</cat>
      <lection>16</lection>
    </Vocabulary>
    <Vocabulary>
      <german>besichtigen</german>
      <japanese>けんがくする</japanese>
      <romaji>見学する</romaji>
      <cat>Verben</cat>
      <lection>16</lection>
    </Vocabulary>
    <Vocabulary>
      <german>jung</german>
      <japanese>わかい</japanese>
      <romaji>若い</romaji>
      <cat>Adjektiv</cat>
      <lection>16</lection>
    </Vocabulary>
    <Vocabulary>
      <german>lang</german>
      <japanese>ながい</japanese>
      <romaji>長い</romaji>
      <cat>Adjektiv</cat>
      <lection>16</lection>
    </Vocabulary>
    <Vocabulary>
      <german>kurz</german>
      <japanese>みしかい</japanese>
      <romaji>短い</romaji>
      <cat>Adjektiv</cat>
      <lection>16</lection>
    </Vocabulary>
    <Vocabulary>
      <german>Körper</german>
      <japanese>からだ</japanese>
      <romaji>体</romaji>
      <cat>Nomen</cat>
      <lection>16</lection>
    </Vocabulary>
    <Vocabulary>
      <german>Kopf</german>
      <japanese>あたま</japanese>
      <romaji>頭</romaji>
      <cat>Nomen</cat>
      <lection>16</lection>
    </Vocabulary>
    <Vocabulary>
      <german>Haare</german>
      <japanese>かみ</japanese>
      <romaji>髪</romaji>
      <cat>Nomen</cat>
      <lection>16</lection>
    </Vocabulary>
    <Vocabulary>
      <german>Gesicht</german>
      <japanese>かお</japanese>
      <romaji>顔</romaji>
      <cat>Nomen</cat>
      <lection>16</lection>
    </Vocabulary>
    <Vocabulary>
      <german>Auge</german>
      <japanese>め</japanese>
      <romaji>目</romaji>
      <cat>Nomen</cat>
      <lection>16</lection>
    </Vocabulary>
    <Vocabulary>
      <german>Ohr</german>
      <japanese>みみ</japanese>
      <romaji>耳</romaji>
      <cat>Nomen</cat>
      <lection>16</lection>
    </Vocabulary>
    <Vocabulary>
      <german>Nase</german>
      <japanese>はな</japanese>
      <romaji>鼻</romaji>
      <cat>Nomen</cat>
      <lection>16</lection>
    </Vocabulary>
    <Vocabulary>
      <german>Mund</german>
      <japanese>くち</japanese>
      <romaji>口</romaji>
      <cat>Nomen</cat>
      <lection>16</lection>
    </Vocabulary>
    <Vocabulary>
      <german>Zahl</german>
      <japanese>は</japanese>
      <romaji>歯</romaji>
      <cat>Nomen</cat>
      <lection>16</lection>
    </Vocabulary>
    <Vocabulary>
      <german>Bauch</german>
      <japanese>おなか</japanese>
      <romaji>お腹</romaji>
      <cat>Nomen</cat>
      <lection>16</lection>
    </Vocabulary>
    <Vocabulary>
      <german>Fuß, Bein</german>
      <japanese>あし</japanese>
      <romaji>足</romaji>
      <cat>Nomen</cat>
      <lection>16</lection>
    </Vocabulary>
    <Vocabulary>
      <german>Körpergröße</german>
      <japanese>せ</japanese>
      <romaji>背</romaji>
      <cat>Nomen</cat>
      <lection>16</lection>
    </Vocabulary>
    <Vocabulary>
      <german>zuerst</german>
      <japanese>まず</japanese>
      <romaji />
      <cat>Adverb</cat>
      <lection>16</lection>
    </Vocabulary>
    <Vocabulary>
      <german>als nächstes</german>
      <japanese>つぎに</japanese>
      <romaji>次に</romaji>
      <cat>Adverb</cat>
      <lection>16</lection>
    </Vocabulary>
    <Vocabulary>
      <german>Geheimnummer</german>
      <japanese>あんしょうばんご</japanese>
      <romaji>暗誦版後</romaji>
      <cat>Nomen</cat>
      <lection>16</lection>
    </Vocabulary>
    <Vocabulary>
      <german>Geldbetrag</german>
      <japanese>きんがく</japanese>
      <romaji>金額</romaji>
      <cat>Nomen</cat>
      <lection>16</lection>
    </Vocabulary>
    <Vocabulary>
      <german>Bestätigung</german>
      <japanese>かくにん</japanese>
      <romaji>確認</romaji>
      <cat>Nomen</cat>
      <lection>16</lection>
    </Vocabulary>
    <Vocabulary>
      <german>lernen</german>
      <japanese>おぼえる</japanese>
      <romaji>覚える</romaji>
      <cat>Verben</cat>
      <lection>17</lection>
    </Vocabulary>
    <Vocabulary>
      <german>vergessen</german>
      <japanese>わすれる</japanese>
      <romaji>忘れる</romaji>
      <cat>Verben</cat>
      <lection>17</lection>
    </Vocabulary>
    <Vocabulary>
      <german>verlieren</german>
      <japanese>なくす</japanese>
      <romaji>なくす</romaji>
      <cat>Verben</cat>
      <lection>17</lection>
    </Vocabulary>
    <Vocabulary>
      <german>bezahlen</german>
      <japanese>はらう</japanese>
      <romaji>払う</romaji>
      <cat>Verben</cat>
      <lection>17</lection>
    </Vocabulary>
    <Vocabulary>
      <german>zurückgeben</german>
      <japanese>かえす</japanese>
      <romaji>返す</romaji>
      <cat>Verben</cat>
      <lection>17</lection>
    </Vocabulary>
    <Vocabulary>
      <german>weggehen</german>
      <japanese>でかける</japanese>
      <romaji>出かける</romaji>
      <cat>Verben</cat>
      <lection>17</lection>
    </Vocabulary>
    <Vocabulary>
      <german>ausziehen</german>
      <japanese>ぬぐ</japanese>
      <romaji>脱ぐ</romaji>
      <cat>Verben</cat>
      <lection>17</lection>
    </Vocabulary>
    <Vocabulary>
      <german>mitnehmen</german>
      <japanese>もっていく</japanese>
      <romaji>持って行く</romaji>
      <cat>Verben</cat>
      <lection>17</lection>
    </Vocabulary>
    <Vocabulary>
      <german>mitbringen</german>
      <japanese>もってくる</japanese>
      <romaji>持ってくる</romaji>
      <cat>Verben</cat>
      <lection>17</lection>
    </Vocabulary>
    <Vocabulary>
      <german>sich sorgen</german>
      <japanese>しんぱいする</japanese>
      <romaji>心配する</romaji>
      <cat>Verben</cat>
      <lection>17</lection>
    </Vocabulary>
    <Vocabulary>
      <german>Überstunden machen</german>
      <japanese>ざんきょうする</japanese>
      <romaji>残響する</romaji>
      <cat>Verben</cat>
      <lection>17</lection>
    </Vocabulary>
    <Vocabulary>
      <german>eine Dienstreise machen</german>
      <japanese>しゅっちょうする</japanese>
      <romaji>出張する</romaji>
      <cat>Verben</cat>
      <lection>17</lection>
    </Vocabulary>
    <Vocabulary>
      <german>Medizin</german>
      <japanese>くすり</japanese>
      <romaji>薬</romaji>
      <cat>Nomen</cat>
      <lection>17</lection>
    </Vocabulary>
    <Vocabulary>
      <german>wichtig</german>
      <japanese>たいせつ</japanese>
      <romaji>大切</romaji>
      <cat>Adjektiv</cat>
      <lection>17</lection>
    </Vocabulary>
    <Vocabulary>
      <german>gefährlich</german>
      <japanese>あぶない</japanese>
      <romaji>危ない</romaji>
      <cat>Adjektiv</cat>
      <lection>17</lection>
    </Vocabulary>
    <Vocabulary>
      <german>Rauchverbot</german>
      <japanese>きんえん</japanese>
      <romaji>禁煙</romaji>
      <cat>Nomen</cat>
      <lection>17</lection>
    </Vocabulary>
    <Vocabulary>
      <german>Fieber</german>
      <japanese>ねつ</japanese>
      <romaji>熱</romaji>
      <cat>Nomen</cat>
      <lection>17</lection>
    </Vocabulary>
    <Vocabulary>
      <german>Krankheit</german>
      <japanese>ひょうき</japanese>
      <romaji>表記</romaji>
      <cat>Nomen</cat>
      <lection>17</lection>
    </Vocabulary>
    <Vocabulary>
      <german>Jacke</german>
      <japanese>うわぎ</japanese>
      <romaji>上着</romaji>
      <cat>Nomen</cat>
      <lection>17</lection>
    </Vocabulary>
    <Vocabulary>
      <german>Unterwäsche</german>
      <japanese>したぎ</japanese>
      <romaji>下着</romaji>
      <cat>Nomen</cat>
      <lection>17</lection>
    </Vocabulary>
    <Vocabulary>
      <german>deshalb</german>
      <japanese>ですから</japanese>
      <romaji>ですから</romaji>
      <cat>Ausdruck</cat>
      <lection>17</lection>
    </Vocabulary>
    <Vocabulary>
      <german>Hals</german>
      <japanese>のど</japanese>
      <romaji>のど</romaji>
      <cat>Nomen</cat>
      <lection>17</lection>
    </Vocabulary>
    <Vocabulary>
      <german>Erkältung</german>
      <japanese>かぜ</japanese>
      <romaji>かぜ</romaji>
      <cat>Nomen</cat>
      <lection>17</lection>
    </Vocabulary>
    <Vocabulary>
      <german>Gute Besserung!</german>
      <japanese>おだいじに</japanese>
      <romaji>お大事に</romaji>
      <cat>Ausdruck</cat>
      <lection>17</lection>
    </Vocabulary>
  </Database>
</VocabularyDatabase>