<?xml version="1.0" encoding="utf-8"?>
<VocabularyDatabase xmlns:xsi="http://www.w3.org/2001/XMLSchema-instance" xmlns:xsd="http://www.w3.org/2001/XMLSchema">
  <Database>
    <Vocabulary>
      <german>Guten Tag</german>
      <japanese>こんにちは</japanese>
      <romaji>konnichiha</romaji>
      <cat>Ausdruck</cat>
      <lection>1</lection>
    </Vocabulary>
    <Vocabulary>
      <german>Guten Abend</german>
      <japanese>こんばんは</japanese>
      <romaji>konbanha</romaji>
      <cat>Ausdruck</cat>
      <lection>1</lection>
    </Vocabulary>
    <Vocabulary>
      <german>Guten Morgen</german>
      <japanese>おはようございます</japanese>
      <romaji>ohayoo gozaimasu</romaji>
      <cat>Ausdruck</cat>
      <lection>1</lection>
    </Vocabulary>
    <Vocabulary>
      <german>aufstehen</german>
      <japanese>おきます</japanese>
      <romaji>okimasu</romaji>
      <cat>Verben</cat>
      <lection>9</lection>
    </Vocabulary>
    <Vocabulary>
      <german>schlafen</german>
      <japanese>ねます</japanese>
      <romaji>nemasu</romaji>
      <cat>Verben</cat>
      <lection>9</lection>
    </Vocabulary>
    <Vocabulary>
      <german>machen</german>
      <japanese>します</japanese>
      <romaji>shimasu</romaji>
      <cat>Verben</cat>
      <lection>9</lection>
    </Vocabulary>
    <Vocabulary>
      <german>gehen</german>
      <japanese>行きます</japanese>
      <romaji>ikimasu</romaji>
      <cat>Verben</cat>
      <lection>9</lection>
    </Vocabulary>
    <Vocabulary>
      <german>lernen</german>
      <japanese>べんきょうします</japanese>
      <romaji>benkyoo-shimasu</romaji>
      <cat>Verben</cat>
      <lection>9</lection>
    </Vocabulary>
    <Vocabulary>
      <german>sehen</german>
      <japanese>見ます</japanese>
      <romaji>mimasu</romaji>
      <cat>Verben</cat>
      <lection>9</lection>
    </Vocabulary>
    <Vocabulary>
      <german>hören</german>
      <japanese>聞きます</japanese>
      <romaji>kikimasu</romaji>
      <cat>Verben</cat>
      <lection>9</lection>
    </Vocabulary>
    <Vocabulary>
      <german>lesen</german>
      <japanese>読みます</japanese>
      <romaji>yomimasu</romaji>
      <cat>Verben</cat>
      <lection>9</lection>
    </Vocabulary>
    <Vocabulary>
      <german>schreiben</german>
      <japanese>書きます</japanese>
      <romaji>kakimasu</romaji>
      <cat>Verben</cat>
      <lection>9</lection>
    </Vocabulary>
    <Vocabulary>
      <german>hineinsteigen</german>
      <japanese>はいります</japanese>
      <romaji>hairimasu</romaji>
      <cat>Verben</cat>
      <lection>9</lection>
    </Vocabulary>
    <Vocabulary>
      <german>baden</german>
      <japanese>おふろ　に　はいります</japanese>
      <romaji>ofuro ni hairimasu</romaji>
      <cat>Verben</cat>
      <lection>9</lection>
    </Vocabulary>
    <Vocabulary>
      <german>heimkehren</german>
      <japanese>帰ります</japanese>
      <romaji>kaerimasu</romaji>
      <cat>Verben</cat>
      <lection>9</lection>
    </Vocabulary>
    <Vocabulary>
      <german>Sport</german>
      <japanese>うんどう</japanese>
      <romaji>undoo</romaji>
      <cat>Nomen</cat>
      <lection>9</lection>
    </Vocabulary>
    <Vocabulary>
      <german>Firma</german>
      <japanese>かいしゃ</japanese>
      <romaji>kaisha</romaji>
      <cat>Nomen</cat>
      <lection>9</lection>
    </Vocabulary>
    <Vocabulary>
      <german>Spaziergang</german>
      <japanese>さんぽ</japanese>
      <romaji>sanpo</romaji>
      <cat>Nomen</cat>
      <lection>9</lection>
    </Vocabulary>
    <Vocabulary>
      <german>Schule</german>
      <japanese>がっこう</japanese>
      <romaji>gakkoo</romaji>
      <cat>Nomen</cat>
      <lection>9</lection>
    </Vocabulary>
    <Vocabulary>
      <german>Arbeit</german>
      <japanese>しごと</japanese>
      <romaji>shigoto</romaji>
      <cat>Nomen</cat>
      <lection>1</lection>
    </Vocabulary>
    <Vocabulary>
      <german>Musik</german>
      <japanese>おんがく</japanese>
      <romaji>ongaku</romaji>
      <cat>Nomen</cat>
      <lection>9</lection>
    </Vocabulary>
    <Vocabulary>
      <german>Zeitung</german>
      <japanese>しんぶん</japanese>
      <romaji>shinbun</romaji>
      <cat>Nomen</cat>
      <lection>9</lection>
    </Vocabulary>
    <Vocabulary>
      <german>Tagebuch</german>
      <japanese>にっき</japanese>
      <romaji>nikki</romaji>
      <cat>Nomen</cat>
      <lection>9</lection>
    </Vocabulary>
    <Vocabulary>
      <german>Haushalt</german>
      <japanese>かじ</japanese>
      <romaji>kaji</romaji>
      <cat>Nomen</cat>
      <lection>9</lection>
    </Vocabulary>
    <Vocabulary>
      <german>Badewanne</german>
      <japanese>おふろ</japanese>
      <romaji>ofuro</romaji>
      <cat>Nomen</cat>
      <lection>9</lection>
    </Vocabulary>
    <Vocabulary>
      <german>Haus/Zuhause</german>
      <japanese>うち</japanese>
      <romaji>uchi</romaji>
      <cat>Nomen</cat>
      <lection>9</lection>
    </Vocabulary>
    <Vocabulary>
      <german>jeden Tag</german>
      <japanese>まいにち</japanese>
      <romaji>mainichi</romaji>
      <cat>Zeitwörter</cat>
      <lection>9</lection>
    </Vocabulary>
    <Vocabulary>
      <german>~Uhr</german>
      <japanese>じ</japanese>
      <romaji>ji</romaji>
      <cat>Zeitwörter</cat>
      <lection>9</lection>
    </Vocabulary>
    <Vocabulary>
      <german>30 Minuten nach</german>
      <japanese>はん</japanese>
      <romaji>han</romaji>
      <cat>Zeitwörter</cat>
      <lection>9</lection>
    </Vocabulary>
    <Vocabulary>
      <german>beschäftigt</german>
      <japanese>いそがしい</japanese>
      <romaji>isogashii</romaji>
      <cat>Adjektiv</cat>
      <lection>9</lection>
    </Vocabulary>
    <Vocabulary>
      <german>morgens</german>
      <japanese>あさ</japanese>
      <romaji>asa</romaji>
      <cat>Zeitwörter</cat>
      <lection>9</lection>
    </Vocabulary>
    <Vocabulary>
      <german>mittags</german>
      <japanese>ひる</japanese>
      <romaji>hiru</romaji>
      <cat>Zeitwörter</cat>
      <lection>9</lection>
    </Vocabulary>
    <Vocabulary>
      <german>abends</german>
      <japanese>よる</japanese>
      <romaji>yoru</romaji>
      <cat>Zeitwörter</cat>
      <lection>9</lection>
    </Vocabulary>
    <Vocabulary>
      <german>gegen</german>
      <japanese>ごろ</japanese>
      <romaji>goro</romaji>
      <cat>Zeitwörter</cat>
      <lection>9</lection>
    </Vocabulary>
    <Vocabulary>
      <german>duschen</german>
      <japanese>シャワー を　あびます</japanese>
      <romaji>shawaa o abimasu</romaji>
      <cat>Verben</cat>
      <lection>9</lection>
    </Vocabulary>
    <Vocabulary>
      <german>~Minute</german>
      <japanese>ぷん　/ ふん</japanese>
      <romaji>pun / fun</romaji>
      <cat>Zeitwörter</cat>
      <lection>9</lection>
    </Vocabulary>
    <Vocabulary>
      <german>a.m.</german>
      <japanese>ごぜん</japanese>
      <romaji>gozen</romaji>
      <cat>Zeitwörter</cat>
      <lection>9</lection>
    </Vocabulary>
    <Vocabulary>
      <german>p.m.</german>
      <japanese>ごご</japanese>
      <romaji>gogo</romaji>
      <cat>Zeitwörter</cat>
      <lection>9</lection>
    </Vocabulary>
    <Vocabulary>
      <german>Tagesablauf</german>
      <japanese>いちにち</japanese>
      <romaji>ichinichi</romaji>
      <cat>Nomen</cat>
      <lection>9</lection>
    </Vocabulary>
    <Vocabulary>
      <german>Mahlzeit</german>
      <japanese>しょくじ</japanese>
      <romaji>shokuji</romaji>
      <cat>Nomen</cat>
      <lection>10</lection>
    </Vocabulary>
    <Vocabulary>
      <german>Einkaufen</german>
      <japanese>かいもの</japanese>
      <romaji>kaimono</romaji>
      <cat>Nomen</cat>
      <lection>10</lection>
    </Vocabulary>
    <Vocabulary>
      <german>Krankenhaus</german>
      <japanese>びょういん</japanese>
      <romaji>byooin</romaji>
      <cat>Nomen</cat>
      <lection>10</lection>
    </Vocabulary>
    <Vocabulary>
      <german>Kunstmuseum</german>
      <japanese>びじゅつかん</japanese>
      <romaji>bijutsukan</romaji>
      <cat>Nomen</cat>
      <lection>10</lection>
    </Vocabulary>
    <Vocabulary>
      <german>Montag</german>
      <japanese>月よう日</japanese>
      <romaji>getsuyoobi</romaji>
      <cat>Zeitwörter</cat>
      <lection>10</lection>
    </Vocabulary>
    <Vocabulary>
      <german>Dienstag</german>
      <japanese>火よう日</japanese>
      <romaji>kayoobi</romaji>
      <cat>Zeitwörter</cat>
      <lection>10</lection>
    </Vocabulary>
    <Vocabulary>
      <german>Mittwoch</german>
      <japanese>水よう日</japanese>
      <romaji>suiyoobi</romaji>
      <cat>Zeitwörter</cat>
      <lection>10</lection>
    </Vocabulary>
    <Vocabulary>
      <german>Donnerstag</german>
      <japanese>木よう日</japanese>
      <romaji>mokuyoobi</romaji>
      <cat>Zeitwörter</cat>
      <lection>10</lection>
    </Vocabulary>
    <Vocabulary>
      <german>Freitag</german>
      <japanese>金よう日</japanese>
      <romaji>Kin'yoobi</romaji>
      <cat>Zeitwörter</cat>
      <lection>10</lection>
    </Vocabulary>
    <Vocabulary>
      <german>Samstag</german>
      <japanese>土よう日</japanese>
      <romaji>doyoobi</romaji>
      <cat>Zeitwörter</cat>
      <lection>10</lection>
    </Vocabulary>
    <Vocabulary>
      <german>Sonntag</german>
      <japanese>日よう日</japanese>
      <romaji>nichiyoobi</romaji>
      <cat>Zeitwörter</cat>
      <lection>10</lection>
    </Vocabulary>
    <Vocabulary>
      <german>Letzte Woche</german>
      <japanese>せんしゅう</japanese>
      <romaji>senshuu</romaji>
      <cat>Zeitwörter</cat>
      <lection>10</lection>
    </Vocabulary>
    <Vocabulary>
      <german>Diese Woche</german>
      <japanese>こんしゅう</japanese>
      <romaji>konshuu</romaji>
      <cat>Zeitwörter</cat>
      <lection>10</lection>
    </Vocabulary>
    <Vocabulary>
      <german>Nächste Woche</german>
      <japanese>らいしゅう</japanese>
      <romaji>raishuu</romaji>
      <cat>Zeitwörter</cat>
      <lection>10</lection>
    </Vocabulary>
    <Vocabulary>
      <german>gestern</german>
      <japanese>きのう</japanese>
      <romaji>kinoo</romaji>
      <cat>Zeitwörter</cat>
      <lection>10</lection>
    </Vocabulary>
    <Vocabulary>
      <german>heute</german>
      <japanese>きょう</japanese>
      <romaji>kyoo</romaji>
      <cat>Zeitwörter</cat>
      <lection>10</lection>
    </Vocabulary>
    <Vocabulary>
      <german>morgen</german>
      <japanese>あした</japanese>
      <romaji>ashita</romaji>
      <cat>Zeitwörter</cat>
      <lection>10</lection>
    </Vocabulary>
    <Vocabulary>
      <german>ausruhen</german>
      <japanese>やすみます</japanese>
      <romaji>yasumimasu</romaji>
      <cat>Verben</cat>
      <lection>9</lection>
    </Vocabulary>
    <Vocabulary>
      <german>Universität</german>
      <japanese>だいがく</japanese>
      <romaji>daigaku</romaji>
      <cat>Nomen</cat>
      <lection>1</lection>
    </Vocabulary>
    <Vocabulary>
      <german>Kaufhaus</german>
      <japanese>デパート</japanese>
      <romaji>depaato</romaji>
      <cat>Nomen</cat>
      <lection>11</lection>
    </Vocabulary>
    <Vocabulary>
      <german>draußen</german>
      <japanese>そと</japanese>
      <romaji>soto</romaji>
      <cat>Adjektiv</cat>
      <lection>11</lection>
    </Vocabulary>
    <Vocabulary>
      <german>Raum / Zimmer</german>
      <japanese>へや</japanese>
      <romaji>heya</romaji>
      <cat>Nomen</cat>
      <lection>11</lection>
    </Vocabulary>
    <Vocabulary>
      <german>Toilette</german>
      <japanese>トイレ</japanese>
      <romaji>toire</romaji>
      <cat>Nomen</cat>
      <lection>11</lection>
    </Vocabulary>
    <Vocabulary>
      <german>Park</german>
      <japanese>こうえん</japanese>
      <romaji>kooen</romaji>
      <cat>Nomen</cat>
      <lection>11</lection>
    </Vocabulary>
    <Vocabulary>
      <german>Tempel</german>
      <japanese>おてら</japanese>
      <romaji>otera</romaji>
      <cat>Nomen</cat>
      <lection>11</lection>
    </Vocabulary>
    <Vocabulary>
      <german>Bahnhof</german>
      <japanese>えき</japanese>
      <romaji>eki</romaji>
      <cat>Nomen</cat>
      <lection>11</lection>
    </Vocabulary>
    <Vocabulary>
      <german>Film</german>
      <japanese>えいが</japanese>
      <romaji>eega</romaji>
      <cat>Nomen</cat>
      <lection>11</lection>
    </Vocabulary>
    <Vocabulary>
      <german>Fremdsprache</german>
      <japanese>がいこく語</japanese>
      <romaji>daikokugo</romaji>
      <cat>Nomen</cat>
      <lection>11</lection>
    </Vocabulary>
    <Vocabulary>
      <german>Fotografie</german>
      <japanese>しゃしん</japanese>
      <romaji>shashin</romaji>
      <cat>Nomen</cat>
      <lection>11</lection>
    </Vocabulary>
    <Vocabulary>
      <german>nehmen</german>
      <japanese>とります</japanese>
      <romaji>torimasu</romaji>
      <cat>Verben</cat>
      <lection>11</lection>
    </Vocabulary>
    <Vocabulary>
      <german>langsam</german>
      <japanese>ゆっくり</japanese>
      <romaji>yukkuri</romaji>
      <cat>Adverb</cat>
      <lection>11</lection>
    </Vocabulary>
    <Vocabulary>
      <german>Plan</german>
      <japanese>よてい</japanese>
      <romaji>yotee</romaji>
      <cat>Nomen</cat>
      <lection>11</lection>
    </Vocabulary>
    <Vocabulary>
      <german>Überstunde</german>
      <japanese>ざんきょう</japanese>
      <romaji>zankyoo</romaji>
      <cat>Nomen</cat>
      <lection>11</lection>
    </Vocabulary>
    <Vocabulary>
      <german>Terminkalender</german>
      <japanese>てちょう</japanese>
      <romaji>techoo</romaji>
      <cat>Nomen</cat>
      <lection>11</lection>
    </Vocabulary>
    <Vocabulary>
      <german>gut passen</german>
      <japanese>いいです</japanese>
      <romaji>iidesu</romaji>
      <cat>Verben</cat>
      <lection>10</lection>
    </Vocabulary>
    <Vocabulary>
      <german>nicht passen</german>
      <japanese>だめです</japanese>
      <romaji>dame desu</romaji>
      <cat>Verben</cat>
      <lection>10</lection>
    </Vocabulary>
    <Vocabulary>
      <german>in Ordnung sein</german>
      <japanese>だいじょうぶです</japanese>
      <romaji>daijoobu desu</romaji>
      <cat>Verben</cat>
      <lection>10</lection>
    </Vocabulary>
    <Vocabulary>
      <german>immer passen</german>
      <japanese>いつでも　いいです</japanese>
      <romaji>itsudemo iidesu</romaji>
      <cat>Verben</cat>
      <lection>10</lection>
    </Vocabulary>
    <Vocabulary>
      <german>Regen</german>
      <japanese>あめ</japanese>
      <romaji>ame</romaji>
      <cat>Nomen</cat>
      <lection>Andere</lection>
    </Vocabulary>
    <Vocabulary>
      <german>Wind</german>
      <japanese>かぜ</japanese>
      <romaji>kaze</romaji>
      <cat>Nomen</cat>
      <lection>Andere</lection>
    </Vocabulary>
    <Vocabulary>
      <german>Wetter</german>
      <japanese>てんき</japanese>
      <romaji>tenki</romaji>
      <cat>Nomen</cat>
      <lection>Andere</lection>
    </Vocabulary>
    <Vocabulary>
      <german>Liebesgeschichte</german>
      <japanese>れんあい</japanese>
      <romaji>ren'ai</romaji>
      <cat>Nomen</cat>
      <lection>11</lection>
    </Vocabulary>
    <Vocabulary>
      <german>Klassik</german>
      <japanese>クラシック</japanese>
      <romaji>kurasikku</romaji>
      <cat>Nomen</cat>
      <lection>11</lection>
    </Vocabulary>
    <Vocabulary>
      <german>Action</german>
      <japanese>アクション</japanese>
      <romaji>akushion</romaji>
      <cat>Nomen</cat>
      <lection>11</lection>
    </Vocabulary>
    <Vocabulary>
      <german>Baseball</german>
      <japanese>やきゅう</japanese>
      <romaji>yakyuu</romaji>
      <cat>Nomen</cat>
      <lection>11</lection>
    </Vocabulary>
    <Vocabulary>
      <german>Judo</german>
      <japanese>じゅうどう</japanese>
      <romaji>juudoo</romaji>
      <cat>Nomen</cat>
      <lection>11</lection>
    </Vocabulary>
    <Vocabulary>
      <german>Hobby</german>
      <japanese>しゅみ</japanese>
      <romaji>shumi</romaji>
      <cat>Nomen</cat>
      <lection>11</lection>
    </Vocabulary>
    <Vocabulary>
      <german>sprechen</german>
      <japanese>話します</japanese>
      <romaji>hanachimasu</romaji>
      <cat>Verben</cat>
      <lection>11</lection>
    </Vocabulary>
    <Vocabulary>
      <german>sagen</german>
      <japanese>言います</japanese>
      <romaji>iimasu</romaji>
      <cat>Verben</cat>
      <lection>11</lection>
    </Vocabulary>
    <Vocabulary>
      <german>~Monat</german>
      <japanese>月</japanese>
      <romaji>gatsu</romaji>
      <cat>Zeitwörter</cat>
      <lection>11</lection>
    </Vocabulary>
    <Vocabulary>
      <german>~Tag</german>
      <japanese>日</japanese>
      <romaji>nichi</romaji>
      <cat>Zeitwörter</cat>
      <lection>11</lection>
    </Vocabulary>
    <Vocabulary>
      <german>Erster im Monat</german>
      <japanese>ついたち</japanese>
      <romaji>tsuitachi</romaji>
      <cat>Zeitwörter</cat>
      <lection>11</lection>
    </Vocabulary>
    <Vocabulary>
      <german>Zweiter im Monat</german>
      <japanese>ふつか</japanese>
      <romaji>futsuka</romaji>
      <cat>Zeitwörter</cat>
      <lection>11</lection>
    </Vocabulary>
    <Vocabulary>
      <german>Dritter im Monat</german>
      <japanese>みっか</japanese>
      <romaji>mikka</romaji>
      <cat>Zeitwörter</cat>
      <lection>11</lection>
    </Vocabulary>
    <Vocabulary>
      <german>Vierter im Monat</german>
      <japanese>よっか</japanese>
      <romaji>yokka</romaji>
      <cat>Zeitwörter</cat>
      <lection>11</lection>
    </Vocabulary>
    <Vocabulary>
      <german>Fünfter im Monat</german>
      <japanese>いつか</japanese>
      <romaji>itsuka</romaji>
      <cat>Zeitwörter</cat>
      <lection>11</lection>
    </Vocabulary>
    <Vocabulary>
      <german>Sechster im Monat</german>
      <japanese>むいか</japanese>
      <romaji>muika</romaji>
      <cat>Zeitwörter</cat>
      <lection>11</lection>
    </Vocabulary>
    <Vocabulary>
      <german>Siebter im Monat</german>
      <japanese>なのか</japanese>
      <romaji>nanoka</romaji>
      <cat>Zeitwörter</cat>
      <lection>11</lection>
    </Vocabulary>
    <Vocabulary>
      <german>Achter im Monat</german>
      <japanese>ようか</japanese>
      <romaji>yooka</romaji>
      <cat>Zeitwörter</cat>
      <lection>11</lection>
    </Vocabulary>
    <Vocabulary>
      <german>Neunter im Monat</german>
      <japanese>ここのか</japanese>
      <romaji>kokonoka</romaji>
      <cat>Zeitwörter</cat>
      <lection>11</lection>
    </Vocabulary>
    <Vocabulary>
      <german>Zehnter im Monat</german>
      <japanese>とおか</japanese>
      <romaji>tooka</romaji>
      <cat>Zeitwörter</cat>
      <lection>11</lection>
    </Vocabulary>
    <Vocabulary>
      <german>wann</german>
      <japanese>いつ</japanese>
      <romaji>itsu</romaji>
      <cat>Fragewörter</cat>
      <lection>10</lection>
    </Vocabulary>
    <Vocabulary>
      <german>a</german>
      <japanese>ア</japanese>
      <romaji>a</romaji>
      <cat>Schriftzeichen</cat>
      <lection>Katakana</lection>
    </Vocabulary>
    <Vocabulary>
      <german>i</german>
      <japanese>イ</japanese>
      <romaji>i</romaji>
      <cat>Schriftzeichen</cat>
      <lection>Katakana</lection>
    </Vocabulary>
    <Vocabulary>
      <german>u</german>
      <japanese>ウ</japanese>
      <romaji>u</romaji>
      <cat>Schriftzeichen</cat>
      <lection>Katakana</lection>
    </Vocabulary>
    <Vocabulary>
      <german>e</german>
      <japanese>エ</japanese>
      <romaji>e</romaji>
      <cat>Schriftzeichen</cat>
      <lection>Katakana</lection>
    </Vocabulary>
    <Vocabulary>
      <german>o</german>
      <japanese>オ</japanese>
      <romaji>o</romaji>
      <cat>Schriftzeichen</cat>
      <lection>Katakana</lection>
    </Vocabulary>
    <Vocabulary>
      <german>ka</german>
      <japanese>カ</japanese>
      <romaji>ka</romaji>
      <cat>Schriftzeichen</cat>
      <lection>Katakana</lection>
    </Vocabulary>
    <Vocabulary>
      <german>ki</german>
      <japanese>キ</japanese>
      <romaji>ki</romaji>
      <cat>Schriftzeichen</cat>
      <lection>Katakana</lection>
    </Vocabulary>
    <Vocabulary>
      <german>ku</german>
      <japanese>ク</japanese>
      <romaji>ku</romaji>
      <cat>Schriftzeichen</cat>
      <lection>Katakana</lection>
    </Vocabulary>
    <Vocabulary>
      <german>ke</german>
      <japanese>ケ</japanese>
      <romaji>ke</romaji>
      <cat>Schriftzeichen</cat>
      <lection>Katakana</lection>
    </Vocabulary>
    <Vocabulary>
      <german>ko</german>
      <japanese>コ</japanese>
      <romaji>ko</romaji>
      <cat>Schriftzeichen</cat>
      <lection>Katakana</lection>
    </Vocabulary>
    <Vocabulary>
      <german>sa</german>
      <japanese>サ</japanese>
      <romaji>sa</romaji>
      <cat>Schriftzeichen</cat>
      <lection>Katakana</lection>
    </Vocabulary>
    <Vocabulary>
      <german>shi</german>
      <japanese>シ</japanese>
      <romaji>shi</romaji>
      <cat>Schriftzeichen</cat>
      <lection>Katakana</lection>
    </Vocabulary>
    <Vocabulary>
      <german>su</german>
      <japanese>ス</japanese>
      <romaji>su</romaji>
      <cat>Schriftzeichen</cat>
      <lection>Katakana</lection>
    </Vocabulary>
    <Vocabulary>
      <german>se</german>
      <japanese>セ</japanese>
      <romaji>se</romaji>
      <cat>Schriftzeichen</cat>
      <lection>Katakana</lection>
    </Vocabulary>
    <Vocabulary>
      <german>so</german>
      <japanese>ソ</japanese>
      <romaji>so</romaji>
      <cat>Schriftzeichen</cat>
      <lection>Katakana</lection>
    </Vocabulary>
    <Vocabulary>
      <german>ta</german>
      <japanese>タ</japanese>
      <romaji>ta</romaji>
      <cat>Schriftzeichen</cat>
      <lection>Katakana</lection>
    </Vocabulary>
    <Vocabulary>
      <german>chi</german>
      <japanese>チ</japanese>
      <romaji>chi</romaji>
      <cat>Schriftzeichen</cat>
      <lection>Katakana</lection>
    </Vocabulary>
    <Vocabulary>
      <german>tsu</german>
      <japanese>ツ</japanese>
      <romaji>tsu</romaji>
      <cat>Schriftzeichen</cat>
      <lection>Katakana</lection>
    </Vocabulary>
    <Vocabulary>
      <german>te</german>
      <japanese>テ</japanese>
      <romaji>te</romaji>
      <cat>Schriftzeichen</cat>
      <lection>Katakana</lection>
    </Vocabulary>
    <Vocabulary>
      <german>to</german>
      <japanese>ト</japanese>
      <romaji>to</romaji>
      <cat>Schriftzeichen</cat>
      <lection>Katakana</lection>
    </Vocabulary>
    <Vocabulary>
      <german>na</german>
      <japanese>ナ</japanese>
      <romaji>na</romaji>
      <cat>Schriftzeichen</cat>
      <lection>Katakana</lection>
    </Vocabulary>
    <Vocabulary>
      <german>ni</german>
      <japanese>ニ</japanese>
      <romaji>ni</romaji>
      <cat>Schriftzeichen</cat>
      <lection>Katakana</lection>
    </Vocabulary>
    <Vocabulary>
      <german>nu</german>
      <japanese>ヌ</japanese>
      <romaji>nu</romaji>
      <cat>Schriftzeichen</cat>
      <lection>Katakana</lection>
    </Vocabulary>
    <Vocabulary>
      <german>ne</german>
      <japanese>ネ</japanese>
      <romaji>ne</romaji>
      <cat>Schriftzeichen</cat>
      <lection>Katakana</lection>
    </Vocabulary>
    <Vocabulary>
      <german>no</german>
      <japanese>ノ</japanese>
      <romaji>no</romaji>
      <cat>Schriftzeichen</cat>
      <lection>Katakana</lection>
    </Vocabulary>
    <Vocabulary>
      <german>ha</german>
      <japanese>ハ</japanese>
      <romaji>ha</romaji>
      <cat>Schriftzeichen</cat>
      <lection>Katakana</lection>
    </Vocabulary>
    <Vocabulary>
      <german>hi</german>
      <japanese>ヒ</japanese>
      <romaji>hi</romaji>
      <cat>Schriftzeichen</cat>
      <lection>Katakana</lection>
    </Vocabulary>
    <Vocabulary>
      <german>fu</german>
      <japanese>フ</japanese>
      <romaji>fu</romaji>
      <cat>Schriftzeichen</cat>
      <lection>Katakana</lection>
    </Vocabulary>
    <Vocabulary>
      <german>he</german>
      <japanese>ヘ</japanese>
      <romaji>he</romaji>
      <cat>Schriftzeichen</cat>
      <lection>Katakana</lection>
    </Vocabulary>
    <Vocabulary>
      <german>ho</german>
      <japanese>ホ</japanese>
      <romaji>ho</romaji>
      <cat>Schriftzeichen</cat>
      <lection>Katakana</lection>
    </Vocabulary>
    <Vocabulary>
      <german>ma</german>
      <japanese>マ</japanese>
      <romaji>ma</romaji>
      <cat>Schriftzeichen</cat>
      <lection>Katakana</lection>
    </Vocabulary>
    <Vocabulary>
      <german>mi</german>
      <japanese>ミ</japanese>
      <romaji>mi</romaji>
      <cat>Schriftzeichen</cat>
      <lection>Katakana</lection>
    </Vocabulary>
    <Vocabulary>
      <german>mu</german>
      <japanese>ム</japanese>
      <romaji>mu</romaji>
      <cat>Schriftzeichen</cat>
      <lection>Katakana</lection>
    </Vocabulary>
    <Vocabulary>
      <german>me</german>
      <japanese>メ</japanese>
      <romaji>me</romaji>
      <cat>Schriftzeichen</cat>
      <lection>Katakana</lection>
    </Vocabulary>
    <Vocabulary>
      <german>mo</german>
      <japanese>モ</japanese>
      <romaji>mo</romaji>
      <cat>Schriftzeichen</cat>
      <lection>Katakana</lection>
    </Vocabulary>
    <Vocabulary>
      <german>yo</german>
      <japanese>ヨ</japanese>
      <romaji>yo</romaji>
      <cat>Schriftzeichen</cat>
      <lection>Katakana</lection>
    </Vocabulary>
    <Vocabulary>
      <german>yu</german>
      <japanese>ユ</japanese>
      <romaji>yu</romaji>
      <cat>Schriftzeichen</cat>
      <lection>Katakana</lection>
    </Vocabulary>
    <Vocabulary>
      <german>ya</german>
      <japanese>ヤ</japanese>
      <romaji>ya</romaji>
      <cat>Schriftzeichen</cat>
      <lection>Katakana</lection>
    </Vocabulary>
    <Vocabulary>
      <german>ra</german>
      <japanese>ラ</japanese>
      <romaji>ra</romaji>
      <cat>Schriftzeichen</cat>
      <lection>Katakana</lection>
    </Vocabulary>
    <Vocabulary>
      <german>ri</german>
      <japanese>リ</japanese>
      <romaji>ri</romaji>
      <cat>Schriftzeichen</cat>
      <lection>Katakana</lection>
    </Vocabulary>
    <Vocabulary>
      <german>ru</german>
      <japanese>ル</japanese>
      <romaji>ru</romaji>
      <cat>Schriftzeichen</cat>
      <lection>Katakana</lection>
    </Vocabulary>
    <Vocabulary>
      <german>re</german>
      <japanese>レ</japanese>
      <romaji>re</romaji>
      <cat>Schriftzeichen</cat>
      <lection>Katakana</lection>
    </Vocabulary>
    <Vocabulary>
      <german>ro</german>
      <japanese>ロ</japanese>
      <romaji>ro</romaji>
      <cat>Schriftzeichen</cat>
      <lection>Katakana</lection>
    </Vocabulary>
    <Vocabulary>
      <german>wa</german>
      <japanese>ワ</japanese>
      <romaji>wa</romaji>
      <cat>Schriftzeichen</cat>
      <lection>Katakana</lection>
    </Vocabulary>
    <Vocabulary>
      <german>wo</german>
      <japanese>ヲ</japanese>
      <romaji>wo</romaji>
      <cat>Schriftzeichen</cat>
      <lection>Katakana</lection>
    </Vocabulary>
    <Vocabulary>
      <german>n</german>
      <japanese>ン</japanese>
      <romaji>n</romaji>
      <cat>Schriftzeichen</cat>
      <lection>Katakana</lection>
    </Vocabulary>
    <Vocabulary>
      <german>Gericht</german>
      <japanese>りょうり</japanese>
      <romaji>ryoori</romaji>
      <cat>Nomen</cat>
      <lection>6</lection>
    </Vocabulary>
    <Vocabulary>
      <german>lieblings~</german>
      <japanese>すきな</japanese>
      <romaji>sukina</romaji>
      <cat>Präfix</cat>
      <lection>6</lection>
    </Vocabulary>
    <Vocabulary>
      <german>nicht gern</german>
      <japanese>きらいな</japanese>
      <romaji>kiraina</romaji>
      <cat>Präfix</cat>
      <lection>6</lection>
    </Vocabulary>
    <Vocabulary>
      <german>Geschäft</german>
      <japanese>みせ</japanese>
      <romaji>mise</romaji>
      <cat>Nomen</cat>
      <lection>6</lection>
    </Vocabulary>
    <Vocabulary>
      <german>lecker</german>
      <japanese>おいしい</japanese>
      <romaji>oishii</romaji>
      <cat>Adjektiv</cat>
      <lection>6</lection>
    </Vocabulary>
    <Vocabulary>
      <german>ekelhaft</german>
      <japanese>まずい</japanese>
      <romaji>mazui</romaji>
      <cat>Adjektiv</cat>
      <lection>6</lection>
    </Vocabulary>
    <Vocabulary>
      <german>teuer</german>
      <japanese>たかい</japanese>
      <romaji>takai</romaji>
      <cat>Adjektiv</cat>
      <lection>6</lection>
    </Vocabulary>
    <Vocabulary>
      <german>billig</german>
      <japanese>やすい</japanese>
      <romaji>yasui</romaji>
      <cat>Adjektiv</cat>
      <lection>6</lection>
    </Vocabulary>
    <Vocabulary>
      <german>schnell / früh</german>
      <japanese>はやい</japanese>
      <romaji>hayai</romaji>
      <cat>Adjektiv</cat>
      <lection>6</lection>
    </Vocabulary>
    <Vocabulary>
      <german>langsam / spät</german>
      <japanese>おそい</japanese>
      <romaji>osoi</romaji>
      <cat>Adjektiv</cat>
      <lection>6</lection>
    </Vocabulary>
    <Vocabulary>
      <german>ein Stück</german>
      <japanese>ひとつ</japanese>
      <romaji>hitotsu</romaji>
      <cat>Stückzahlen</cat>
      <lection>6</lection>
    </Vocabulary>
    <Vocabulary>
      <german>zwei Stück</german>
      <japanese>ふたつ</japanese>
      <romaji>futatsu</romaji>
      <cat>Stückzahlen</cat>
      <lection>6</lection>
    </Vocabulary>
    <Vocabulary>
      <german>drei Stück</german>
      <japanese>みっつ</japanese>
      <romaji>mittsu</romaji>
      <cat>Stückzahlen</cat>
      <lection>6</lection>
    </Vocabulary>
    <Vocabulary>
      <german>vier Stück</german>
      <japanese>よっつ</japanese>
      <romaji>yottsu</romaji>
      <cat>Stückzahlen</cat>
      <lection>6</lection>
    </Vocabulary>
    <Vocabulary>
      <german>fünf Stück</german>
      <japanese>いつつ</japanese>
      <romaji>itsutsu</romaji>
      <cat>Stückzahlen</cat>
      <lection>6</lection>
    </Vocabulary>
    <Vocabulary>
      <german>das Beste~</german>
      <japanese>いちばん</japanese>
      <romaji>ichiban</romaji>
      <cat>Präfix</cat>
      <lection>6</lection>
    </Vocabulary>
    <Vocabulary>
      <german>welcher Art</german>
      <japanese>どんな</japanese>
      <romaji>donna</romaji>
      <cat>Fragewörter</cat>
      <lection>6</lection>
    </Vocabulary>
    <Vocabulary>
      <german>machen sie~</german>
      <japanese>ください</japanese>
      <romaji>kudasai</romaji>
      <cat>Ausdruck</cat>
      <lection>6</lection>
    </Vocabulary>
    <Vocabulary>
      <german>Zeit</german>
      <japanese>じかん</japanese>
      <romaji>jikan</romaji>
      <cat>Nomen</cat>
      <lection>6</lection>
    </Vocabulary>
    <Vocabulary>
      <german>Geld</german>
      <japanese>おかね</japanese>
      <romaji>okane</romaji>
      <cat>Nomen</cat>
      <lection>6</lection>
    </Vocabulary>
    <Vocabulary>
      <german>Mitternacht</german>
      <japanese>れいじ</japanese>
      <romaji>reiji</romaji>
      <cat>Zeitwörter</cat>
      <lection>9</lection>
    </Vocabulary>
    <Vocabulary>
      <german>kommen</german>
      <japanese>来ます</japanese>
      <romaji>kimasu</romaji>
      <cat>Verben</cat>
      <lection>9</lection>
    </Vocabulary>
    <Vocabulary>
      <german> Buch</german>
      <japanese>本</japanese>
      <romaji>hon</romaji>
      <cat>Nomen</cat>
      <lection>9</lection>
    </Vocabulary>
    <Vocabulary>
      <german>immer</german>
      <japanese>いつも</japanese>
      <romaji>itsumo</romaji>
      <cat>Zeitwörter</cat>
      <lection>9</lection>
    </Vocabulary>
    <Vocabulary>
      <german>jetzt</german>
      <japanese>今</japanese>
      <romaji>ima</romaji>
      <cat>Zeitwörter</cat>
      <lection>9</lection>
    </Vocabulary>
    <Vocabulary>
      <german>vorgestern</german>
      <japanese>おととい</japanese>
      <romaji>ototoi</romaji>
      <cat>Zeitwörter</cat>
      <lection>10</lection>
    </Vocabulary>
    <Vocabulary>
      <german>übermorgen</german>
      <japanese>あさって</japanese>
      <romaji>asatte</romaji>
      <cat>Zeitwörter</cat>
      <lection>10</lection>
    </Vocabulary>
    <Vocabulary>
      <german>letzter Monat</german>
      <japanese>先月</japanese>
      <romaji>sengetsu</romaji>
      <cat>Zeitwörter</cat>
      <lection>10</lection>
    </Vocabulary>
    <Vocabulary>
      <german>dieser Monat</german>
      <japanese>今月</japanese>
      <romaji>kongetsu</romaji>
      <cat>Zeitwörter</cat>
      <lection>10</lection>
    </Vocabulary>
    <Vocabulary>
      <german>nächster Monat</german>
      <japanese>来月</japanese>
      <romaji>raigetsu</romaji>
      <cat>Zeitwörter</cat>
      <lection>10</lection>
    </Vocabulary>
    <Vocabulary>
      <german>letztes Jahr</german>
      <japanese>きょねん</japanese>
      <romaji>kyonen</romaji>
      <cat>Zeitwörter</cat>
      <lection>10</lection>
    </Vocabulary>
    <Vocabulary>
      <german>dieses Jahr</german>
      <japanese>ことし</japanese>
      <romaji>kotoshi</romaji>
      <cat>Zeitwörter</cat>
      <lection>10</lection>
    </Vocabulary>
    <Vocabulary>
      <german>nächstes Jahr</german>
      <japanese>らいねん</japanese>
      <romaji>rainen</romaji>
      <cat>Zeitwörter</cat>
      <lection>10</lection>
    </Vocabulary>
    <Vocabulary>
      <german>von ~ bis ~</german>
      <japanese>～から～まで</japanese>
      <romaji>~kara~made</romaji>
      <cat>Ausdruck</cat>
      <lection>10</lection>
    </Vocabulary>
    <Vocabulary>
      <german>Ferien / Pause</german>
      <japanese>休み</japanese>
      <romaji>yasumi</romaji>
      <cat>Nomen</cat>
      <lection>10</lection>
    </Vocabulary>
    <Vocabulary>
      <german>wie</german>
      <japanese>どう</japanese>
      <romaji>doo</romaji>
      <cat>Fragewörter</cat>
      <lection>10</lection>
    </Vocabulary>
    <Vocabulary>
      <german>Geburtstag</german>
      <japanese>たんじょうび</japanese>
      <romaji>tanjoobi</romaji>
      <cat>Nomen</cat>
      <lection>11</lection>
    </Vocabulary>
    <Vocabulary>
      <german>Song</german>
      <japanese>うた</japanese>
      <romaji>uta</romaji>
      <cat>Nomen</cat>
      <lection>11</lection>
    </Vocabulary>
    <Vocabulary>
      <german>singen</german>
      <japanese>うたいます</japanese>
      <romaji>utaimasu</romaji>
      <cat>Verben</cat>
      <lection>11</lection>
    </Vocabulary>
    <Vocabulary>
      <german>Lesen</german>
      <japanese>どくしょ</japanese>
      <romaji>dokusho</romaji>
      <cat>Nomen</cat>
      <lection>11</lection>
    </Vocabulary>
    <Vocabulary>
      <german>Novelle</german>
      <japanese>しょいせつ</japanese>
      <romaji>shoosetsu</romaji>
      <cat>Nomen</cat>
      <lection>11</lection>
    </Vocabulary>
    <Vocabulary>
      <german>Literatur</german>
      <japanese>ぶんがく</japanese>
      <romaji>bungaku</romaji>
      <cat>Nomen</cat>
      <lection>11</lection>
    </Vocabulary>
    <Vocabulary>
      <german>Magazin</german>
      <japanese>ざっし</japanese>
      <romaji>sasshi</romaji>
      <cat>Nomen</cat>
      <lection>11</lection>
    </Vocabulary>
    <Vocabulary>
      <german>Bild</german>
      <japanese>え</japanese>
      <romaji>e</romaji>
      <cat>Nomen</cat>
      <lection>11</lection>
    </Vocabulary>
    <Vocabulary>
      <german>Teezeremonie</german>
      <japanese>さどう</japanese>
      <romaji>sadoo</romaji>
      <cat>Nomen</cat>
      <lection>11</lection>
    </Vocabulary>
    <Vocabulary>
      <german>Gartenarbeit</german>
      <japanese>いけばな</japanese>
      <romaji>ikebana</romaji>
      <cat>Nomen</cat>
      <lection>11</lection>
    </Vocabulary>
    <Vocabulary>
      <german>entspannen</german>
      <japanese>ゆっくりします</japanese>
      <romaji>jukkuri-shimasu</romaji>
      <cat>Verben</cat>
      <lection>11</lection>
    </Vocabulary>
    <Vocabulary>
      <german>Veranstaltung</german>
      <japanese>イベント</japanese>
      <romaji>ibento</romaji>
      <cat>Nomen</cat>
      <lection>12</lection>
    </Vocabulary>
    <Vocabulary>
      <german>Spiel</german>
      <japanese>しあい</japanese>
      <romaji>shiai</romaji>
      <cat>Nomen</cat>
      <lection>12</lection>
    </Vocabulary>
    <Vocabulary>
      <german>Feuerwerk</german>
      <japanese>はなび</japanese>
      <romaji>hanabi</romaji>
      <cat>Nomen</cat>
      <lection>12</lection>
    </Vocabulary>
    <Vocabulary>
      <german>Feiertag</german>
      <japanese>しゅくじつ</japanese>
      <romaji>shukujitsu</romaji>
      <cat>Nomen</cat>
      <lection>12</lection>
    </Vocabulary>
    <Vocabulary>
      <german>Jahreszeit</german>
      <japanese>きせつ</japanese>
      <romaji>kisetsu</romaji>
      <cat>Nomen</cat>
      <lection>12</lection>
    </Vocabulary>
    <Vocabulary>
      <german>Frühling</german>
      <japanese>はる</japanese>
      <romaji>haru</romaji>
      <cat>Nomen</cat>
      <lection>12</lection>
    </Vocabulary>
    <Vocabulary>
      <german>Sommer</german>
      <japanese>なつ</japanese>
      <romaji>natsu</romaji>
      <cat>Nomen</cat>
      <lection>12</lection>
    </Vocabulary>
    <Vocabulary>
      <german>Herbst</german>
      <japanese>あき</japanese>
      <romaji>Herbst</romaji>
      <cat>Nomen</cat>
      <lection>12</lection>
    </Vocabulary>
    <Vocabulary>
      <german>Winter</german>
      <japanese>ふゆ</japanese>
      <romaji>fuyu</romaji>
      <cat>Nomen</cat>
      <lection>12</lection>
    </Vocabulary>
    <Vocabulary>
      <german>Stadt</german>
      <japanese>まち</japanese>
      <romaji>machi</romaji>
      <cat>Nomen</cat>
      <lection>12</lection>
    </Vocabulary>
    <Vocabulary>
      <german>zusammen</german>
      <japanese>いっしょ</japanese>
      <romaji>issho</romaji>
      <cat>Adverb</cat>
      <lection>12</lection>
    </Vocabulary>
    <Vocabulary>
      <german>nächstes mal</german>
      <japanese>こんど</japanese>
      <romaji>kondo</romaji>
      <cat>Zeitwörter</cat>
      <lection>12</lection>
    </Vocabulary>
    <Vocabulary>
      <german>noch einmal</german>
      <japanese>また</japanese>
      <romaji>mata</romaji>
      <cat>Adjektiv</cat>
      <lection>12</lection>
    </Vocabulary>
    <Vocabulary>
      <german>Das ist schade</german>
      <japanese>ざんねん　です</japanese>
      <romaji>zannen desu</romaji>
      <cat>Ausdruck</cat>
      <lection>12</lection>
    </Vocabulary>
    <Vocabulary>
      <german>Selbstverständlich</german>
      <japanese>もちろん</japanese>
      <romaji>mochiron</romaji>
      <cat>Ausdruck</cat>
      <lection>12</lection>
    </Vocabulary>
    <Vocabulary>
      <german>Ich freue mich drauf</german>
      <japanese>たのしみです</japanese>
      <romaji>tanoshimi desu</romaji>
      <cat>Ausdruck</cat>
      <lection>12</lection>
    </Vocabulary>
    <Vocabulary>
      <german>1</german>
      <japanese>一</japanese>
      <romaji>ichi</romaji>
      <cat>Zahlen</cat>
      <lection>10</lection>
    </Vocabulary>
    <Vocabulary>
      <german>2</german>
      <japanese>二</japanese>
      <romaji>ni</romaji>
      <cat>Zahlen</cat>
      <lection>10</lection>
    </Vocabulary>
    <Vocabulary>
      <german>3</german>
      <japanese>三</japanese>
      <romaji>san</romaji>
      <cat>Zahlen</cat>
      <lection>10</lection>
    </Vocabulary>
    <Vocabulary>
      <german>4</german>
      <japanese>四</japanese>
      <romaji>yon</romaji>
      <cat>Zahlen</cat>
      <lection>10</lection>
    </Vocabulary>
    <Vocabulary>
      <german>5</german>
      <japanese>五</japanese>
      <romaji>go</romaji>
      <cat>Zahlen</cat>
      <lection>10</lection>
    </Vocabulary>
    <Vocabulary>
      <german>6</german>
      <japanese>六</japanese>
      <romaji>roku</romaji>
      <cat>Zahlen</cat>
      <lection>10</lection>
    </Vocabulary>
    <Vocabulary>
      <german>7</german>
      <japanese>七</japanese>
      <romaji>nana</romaji>
      <cat>Zahlen</cat>
      <lection>10</lection>
    </Vocabulary>
    <Vocabulary>
      <german>8</german>
      <japanese>八</japanese>
      <romaji>hachi</romaji>
      <cat>Zahlen</cat>
      <lection>10</lection>
    </Vocabulary>
    <Vocabulary>
      <german>9</german>
      <japanese>九</japanese>
      <romaji>kyuu</romaji>
      <cat>Zahlen</cat>
      <lection>10</lection>
    </Vocabulary>
    <Vocabulary>
      <german>10</german>
      <japanese>十</japanese>
      <romaji>juu</romaji>
      <cat>Zahlen</cat>
      <lection>10</lection>
    </Vocabulary>
    <Vocabulary>
      <german>hell</german>
      <japanese>あかるい</japanese>
      <romaji>akarui</romaji>
      <cat>Adjektiv</cat>
      <lection>7</lection>
    </Vocabulary>
    <Vocabulary>
      <german>dunkel</german>
      <japanese>くらい</japanese>
      <romaji>kurai</romaji>
      <cat>Adjektiv</cat>
      <lection>7</lection>
    </Vocabulary>
    <Vocabulary>
      <german>neu</german>
      <japanese>あたらしい</japanese>
      <romaji>atarashii</romaji>
      <cat>Adjektiv</cat>
      <lection>7</lection>
    </Vocabulary>
    <Vocabulary>
      <german>alt</german>
      <japanese>ふるい</japanese>
      <romaji>furui</romaji>
      <cat>Adjektiv</cat>
      <lection>7</lection>
    </Vocabulary>
    <Vocabulary>
      <german>groß</german>
      <japanese>おおきい</japanese>
      <romaji>ookii</romaji>
      <cat>Adjektiv</cat>
      <lection>7</lection>
    </Vocabulary>
    <Vocabulary>
      <german>klein</german>
      <japanese>ちいさい</japanese>
      <romaji>chiisai</romaji>
      <cat>Adjektiv</cat>
      <lection>7</lection>
    </Vocabulary>
    <Vocabulary>
      <german>aufgeräumt/sauber</german>
      <japanese>きれい</japanese>
      <romaji>kiree</romaji>
      <cat>Adjektiv</cat>
      <lection>7</lection>
    </Vocabulary>
    <Vocabulary>
      <german>unaufgeräumt/dreckig</german>
      <japanese>きたない</japanese>
      <romaji>kitanai</romaji>
      <cat>Adjektiv</cat>
      <lection>7</lection>
    </Vocabulary>
    <Vocabulary>
      <german>groß/geräumig</german>
      <japanese>ひろい</japanese>
      <romaji>hiroi</romaji>
      <cat>Adjektiv</cat>
      <lection>7</lection>
    </Vocabulary>
    <Vocabulary>
      <german>klein/schmal</german>
      <japanese>せまい</japanese>
      <romaji>semai</romaji>
      <cat>Adjektiv</cat>
      <lection>7</lection>
    </Vocabulary>
    <Vocabulary>
      <german>toll/gut</german>
      <japanese>いい</japanese>
      <romaji>ii</romaji>
      <cat>Adjektiv</cat>
      <lection>7</lection>
    </Vocabulary>
    <Vocabulary>
      <german>arbeiten</german>
      <japanese>はたらきます</japanese>
      <romaji>hatarakimasu</romaji>
      <cat>Verben</cat>
      <lection>7</lection>
    </Vocabulary>
    <Vocabulary>
      <german>spieler/amüsieren</german>
      <japanese>あそびます</japanese>
      <romaji>asobimasu</romaji>
      <cat>Verben</cat>
      <lection>7</lection>
    </Vocabulary>
    <Vocabulary>
      <german>Reise</german>
      <japanese>りよこう</japanese>
      <romaji>riyokoo</romaji>
      <cat>Nomen</cat>
      <lection>7</lection>
    </Vocabulary>
    <Vocabulary>
      <german>Gesicht waschen</german>
      <japanese>かおを あらいます</japanese>
      <romaji>kao o araimasu</romaji>
      <cat>Verben</cat>
      <lection>9</lection>
    </Vocabulary>
    <Vocabulary>
      <german>Zähne putzen</german>
      <japanese>はを　みがきます</japanese>
      <romaji>ha o migakimasu</romaji>
      <cat>Verben</cat>
      <lection>9</lection>
    </Vocabulary>
    <Vocabulary>
      <german>Make up auftragen</german>
      <japanese>おけしょうを　します</japanese>
      <romaji>okeshoo o shimasu</romaji>
      <cat>Verben</cat>
      <lection>9</lection>
    </Vocabulary>
    <Vocabulary>
      <german>rasieren</german>
      <japanese>ひげを　そります</japanese>
      <romaji>hige o sorimasu</romaji>
      <cat>Verben</cat>
      <lection>9</lection>
    </Vocabulary>
    <Vocabulary>
      <german>sich anziehen</german>
      <japanese>ふくを　きます</japanese>
      <romaji>fuku o kimasu</romaji>
      <cat>Verben</cat>
      <lection>9</lection>
    </Vocabulary>
    <Vocabulary>
      <german>sich ausziehen</german>
      <japanese>ふくを　ぬぎます</japanese>
      <romaji>fuku o nugimasu</romaji>
      <cat>Verben</cat>
      <lection>9</lection>
    </Vocabulary>
    <Vocabulary>
      <german>Wäsche waschen</german>
      <japanese>せんたくを　します</japanese>
      <romaji>sentaku o shimasu</romaji>
      <cat>Verben</cat>
      <lection>9</lection>
    </Vocabulary>
  </Database>
</VocabularyDatabase>